Workbook

Sheet Methodology & Approach
A1: INDEPENDENT ASSESSMENT — METHODOLOGY & APPROACH
A2: SC-GL/6-2023 Guidelines on Technology Risk Management — Capital Market Intermediary
A4: ENGAGEMENT DETAILS
A5: Entity Name: | B5: [Entity Name]
A6: Regulated Activity: | B6: Capital Market Intermediary (CMSL/CMSRL Holder)
A7: Assessment Date: | B7: [DD/MM/YYYY]
A8: Assessment Period: | B8: [Start Date] to [End Date]
A9: Lead Assessor: | B9: [Name, Qualification]
A10: Engagement Reference: | B10: [Ref Number]
A11: Report Classification: | B11: Confidential (Sulit)
A13: SCOPE OF ASSESSMENT
A14: This assessment is conducted pursuant to SC-GL/6-2023 Guidelines on Technology Risk Management for capital market intermediaries regulated by the Securities Commission Malaysia.
A15: The objective is to ascertain that the entity has established and maintains an effective technology risk management framework covering governance, cybersecurity, resilience, third-party management, data protection, and emerging technology risks.
A16: Assessment covers 35 controls across 10 domains: (1) Governance & Oversight, (2) Technology Risk Assessment, (3) Cybersecurity, (4) Business Continuity, (5) Incident Management, (6) Third-Party Risk, (7) Cloud Services, (8) Data Management, (9) Technology Audit, (10) Emerging Technology.
A17: IMPORTANT: Third-party validation does not guarantee SC approval. Areas assessed reflect the assessor's professional judgement guided by SC-GL/6-2023 and may not cover every SC expectation.
A19: ASSESSMENT METHODS
A20: Inspection | B20: Examination of documents, records, policies, configurations, and tangible evidence to verify existence, completeness, and compliance with SC-GL/6-2023 requirements.
A21: Inquiry | B21: Interviews with management, process owners, and staff to understand controls and their operating effectiveness within the capital market entity.
A22: Observation | B22: Direct observation of processes, systems, and activities being performed.
A23: Confirmation | B23: Verification with external or independent parties (e.g., CSP certifications, third-party audit reports).
A25: SAMPLING METHODOLOGY
A26: This assessment uses judgemental (non-statistical) sampling. Sample sizes are determined by population size and control risk tier. The assessor exercises professional judgement in sample selection, prioritising items with higher inherent risk, recent changes, or anomalies identified during the assessment.
A28: Table 1 — Population-Based Sample Sizes
A29: Population Size | B29: Standard Risk | C29: High Risk (Critical Tier) | D29: Rationale
A30: 1–5 | B30: All | C30: All | D30: Full coverage feasible
A31: 6–15 | B31: 3 | C31: 5 | D31: ~25–40% coverage
A32: 16–50 | B32: 5 | C32: 8 | D32: Sufficient for pattern detection
A33: 51–100 | B33: 8 | C33: 12 | D33: Diminishing returns beyond this
A34: 100+ | B34: 10 | C34: 15 | D34: Cap with stratification
A36: Table 2 — Time-Based Evidence Coverage
A37: Evidence Type | B37: Coverage Period | C37: Rationale
A38: Board / committee reports | B38: Last 4 quarters | C38: Full annual governance cycle
A39: Operational records (incidents, changes, patches) | B39: Last 3–6 months | C39: Recent operating effectiveness
A40: Annual processes (risk assessment, DR test, pen test) | B40: Last 12 months | C40: Full cycle
A41: Continuous monitoring (SOC, logs, alerts) | B41: Last 30 days | C41: Current state verification
A42: Policies and frameworks | B42: Current version + prior | C42: Change tracking
A44: Table 3 — Control Risk Tier Classification
A45: Risk Tier | B45: Sampling Level | C45: Description | D45: Controls
A46: Critical | B46: High Risk column | C46: Foundation controls whose failure directly impacts market operations, regulatory standing, or client protection | D46: GRA-1, CYB-2, RIM-1, RIM-2, RIM-5, RIM-6, DET-3
A47: Standard | B47: Standard Risk column | C47: Controls that support effective technology risk management but whose absence has indirect or contained impact | D47: GRA-2–10, CYB-1/3/4, RIM-3/4/7/8, TPC-1–7, DET-1/2
A48: Conditional | B48: Standard Risk (if applicable) | C48: Controls applicable only if the entity engages in specific activities. Mark N/A with justification if not applicable. | D48: DET-4, DET-5, DET-6
A50: CONCLUSION SCALE
A51: Compliant | B51: Control/requirement fully implemented and operating effectively. Evidence supports compliance with SC-GL/6-2023.
A52: Partially Compliant | B52: Implemented but with gaps in scope, coverage, documentation, or effectiveness. Specific improvements required.
A53: Non-Compliant | B53: Absent, fundamentally deficient, or not operating. SC-GL/6-2023 criteria not met.
A54: N/A | B54: Not applicable to entity's operations. Justification documented.
A56: LIMITATIONS
A57: 1. Limited assurance engagement — conclusions based on procedures performed, not an audit opinion.
A58: 2. Point-in-time assessment. Does not guarantee continued compliance.
A59: 3. Reliance on management representations and documentation provided.
A60: 4. Scope guided by SC-GL/6-2023 Guidelines on Technology Risk Management. SC may update requirements.
A61: 5. Does not constitute legal or regulatory advice.
A64: SIGN-OFF
A65: Lead Assessor: | B65: ________________________ | E65: Date: | F65: ______________
A66: Quality Reviewer: | B66: ________________________ | E66: Date: | F66: ______________
A67: Entity Representative: | B67: ________________________ | E67: Date: | F67: ______________

Sheet Governance, Risk & Audit
A1: Ref | B1: Control | C1: Sub-Procedure | D1: Assessment Procedures | E1: Expected Evidence | F1: Method | G1: Procedures Performed | H1: Evidence Obtained | I1: Evidence Ref | J1: Observation / Findings | K1: Conclusion | L1: Recommendations | M1: Score
A2: GRA-1 — Technology Risk Governance Framework [CRITICAL]
A3: PURPOSE: SC-GL/6-2023 requires capital market intermediaries to establish a board-approved technology risk governance framework as the foundation for all technology risk management activities. This control ensures that governance structures, accountability, and oversight mechanisms are in place to protect market integrity, client assets, and operational resilience. EXPECTATION: The assessor should find a formally documented, board-approved governance framework with clearly defined roles and responsibilities, a functioning technology risk committee with cross-functional representation, and evidence of regular board-level engagement with technology risk matters. The framework should be current, reviewed within 12 months, and explicitly aligned with SC-GL/6-2023 requirements. KEY RISK: Without an effective governance framework, technology risk management operates without strategic direction or board accountability, increasing the likelihood of undetected control failures affecting trading operations, settlement integrity, and regulatory standing with the Securities Commission.
A4: GRA-1 | B4: Technology Risk Governance Framework | C4: Governance structure & reporting lines | D4: 1. Obtain the board-approved technology risk governance framework document. 2. Verify it defines governance structure with clear roles, responsibilities, and reporting lines from board level through operational management. 3. Confirm a technology risk committee (or equivalent) exists with cross-functional representation. 4. Review committee meeting minutes (last 4 quarters) for attendance, quorum, and decision-making evidence. | E4: Board-approved governance framework; Technology risk committee charter; Committee meeting minutes (last 4 quarters); Organisational chart showing reporting lines; Committee attendance records | F4: Inspection / Inquiry | M4: =IF(K4="Compliant",3,IF(K4="Partially Compliant",2,IF(K4="Non-Compliant",1,"")))
A5: GRA-1 | B5: Technology Risk Governance Framework | C5: Board approval & annual review cycle | D5: 1. Inspect the governance framework document for board approval evidence (board resolution, signed approval page, or minutes recording approval). 2. Verify the framework version history and confirm the last review date is within 12 months. 3. Determine whether out-of-cycle reviews are triggered by material changes such as new SC guidance, significant incidents, or organisational restructuring. 4. Review board agenda and papers for the most recent annual review to verify the board received adequate information to assess the framework's adequacy. | E5: Board resolution or approval record; Framework version history log; Board meeting agenda and papers for last annual framework review; Out-of-cycle review trigger criteria (if documented) | F5: Inspection | M5: =IF(K5="Compliant",3,IF(K5="Partially Compliant",2,IF(K5="Non-Compliant",1,"")))
A6: GRA-1 | B6: Technology Risk Governance Framework | C6: Three lines of defence model | D6: 1. Interview the CISO or committee chair to understand how the three lines of defence model is implemented for technology risk management. 2. Verify that first line (technology operations and business units), second line (risk management and compliance), and third line (internal audit) roles are clearly delineated and documented. 3. Confirm independence between the lines — specifically that second-line risk oversight is not conflated with first-line technology delivery. 4. Review a sample of 3 risk decisions (per sampling methodology) to trace how the three lines interacted (e.g., risk acceptance, control exception). | E6: Three lines of defence model documentation; RACI matrix for technology risk responsibilities; Sample risk decision records (3) showing line interactions; Organisational chart demonstrating independence between lines | F6: Inspection / Inquiry | M6: =IF(K6="Compliant",3,IF(K6="Partially Compliant",2,IF(K6="Non-Compliant",1,"")))
A7: GRA-1 | B7: Technology Risk Governance Framework | C7: Technology risk appetite statement | D7: 1. Obtain the documented technology risk appetite statement and verify it is aligned with the entity's overall business strategy and risk appetite. 2. Confirm the risk appetite statement addresses capital market-specific risk dimensions (e.g., trading system availability, settlement failure tolerance, market data integrity). 3. Verify the risk appetite has been approved by the board and is reviewed at least annually. 4. Assess whether the risk appetite is operationalised through defined risk tolerance levels and Key Risk Indicators with escalation thresholds. | E7: Board-approved technology risk appetite statement; Risk tolerance levels and KRI threshold definitions; Board approval evidence for risk appetite; Mapping of risk appetite to capital market operational risk dimensions | F7: Inspection | M7: =IF(K7="Compliant",3,IF(K7="Partially Compliant",2,IF(K7="Non-Compliant",1,"")))
A8: GRA-1 | B8: Technology Risk Governance Framework | C8: Committee effectiveness & decision quality | D8: 1. Review technology risk committee meeting minutes from the last 4 quarters for evidence of substantive discussion, challenge, and decision-making. 2. Verify that the committee receives and acts on key inputs: risk reports, incident summaries, audit findings, and emerging risk briefings. 3. Confirm that committee action items are tracked to closure by reviewing the action register. 4. Assess committee membership for appropriate seniority and cross-functional representation including trading, operations, compliance, and technology. | E8: Committee meeting minutes (last 4 quarters); Committee action item register with closure tracking; Committee membership list with roles and seniority; Agenda and supporting papers for last 2 meetings | F8: Inspection | M8: =IF(K8="Compliant",3,IF(K8="Partially Compliant",2,IF(K8="Non-Compliant",1,"")))
A9: GRA-1 | B9: Technology Risk Governance Framework | C9: Alignment with SC-GL/6-2023 requirements | D9: 1. Map the governance framework's coverage against SC-GL/6-2023 guideline requirements for governance and oversight. 2. Identify any gaps where SC expectations are not explicitly addressed in the governance framework. 3. Verify that the framework references SC-GL/6-2023 as the primary regulatory driver and is updated when SC issues new guidance or advisories. 4. Confirm that governance arrangements address SC-specific expectations for capital market intermediaries, including oversight of trading systems, client data protection, and market integrity. | E9: SC-GL/6-2023 coverage mapping or gap analysis; Framework sections referencing SC guidelines; Records of framework updates following SC guidance changes; SC advisory review log | F9: Inspection | M9: =IF(K9="Compliant",3,IF(K9="Partially Compliant",2,IF(K9="Non-Compliant",1,"")))
A10: GRA-2 — CISO Designation & Authority
A11: PURPOSE: SC-GL/6-2023 requires capital market intermediaries to designate a CISO with adequate authority, independence, and resources to oversee cybersecurity and technology risk. This ensures a single accountable executive drives the security programme and has unimpeded access to the board. EXPECTATION: The assessor should find a formally appointed CISO with relevant qualifications and certifications, reporting independently from technology delivery, with demonstrated board access and a standing reporting slot. The CISO should have an adequately resourced team and documented authority to influence technology decisions. KEY RISK: Without a designated, independent CISO, security priorities are subordinated to delivery timelines, creating blind spots in risk oversight that can lead to undetected vulnerabilities in trading systems and delayed incident response.
A12: GRA-2 | B12: CISO Designation & Authority | C12: CISO appointment & qualifications | D12: 1. Obtain the CISO's appointment letter, board resolution, or designation record confirming the formal appointment. 2. Review the CISO's qualifications, professional certifications (e.g., CISSP, CISM), and experience relevant to technology risk and capital market operations. 3. Verify the CISO is appointed on a full-time, dedicated basis and that the role is not combined with technology delivery responsibilities. 4. Confirm the appointment is documented in a job description that defines the scope of authority over all technology and cybersecurity risk domains. | E12: CISO appointment letter or board resolution; CISO curriculum vitae with qualifications and certifications; Job description defining scope and authority; Organisation announcement or HR confirmation of dedicated full-time role | F12: Inspection | M12: =IF(K12="Compliant",3,IF(K12="Partially Compliant",2,IF(K12="Non-Compliant",1,"")))
A13: GRA-2 | B13: CISO Designation & Authority | C13: Reporting independence | D13: 1. Review the organisational chart to confirm the CISO's reporting line is independent from the CTO or Head of IT Operations. 2. Verify the CISO has direct access to senior management and/or board committee without requiring CTO or IT head approval. 3. Interview the CISO to assess the practical reality of independence — specifically whether security recommendations are overridden by technology delivery priorities without appropriate escalation. 4. Confirm escalation procedures exist that allow the CISO to raise unresolved concerns directly to the board if necessary. | E13: Organisational chart showing CISO reporting line; Escalation procedure documentation; CISO interview notes confirming practical independence; Evidence of CISO-board direct communication channel | F13: Inspection / Inquiry | M13: =IF(K13="Compliant",3,IF(K13="Partially Compliant",2,IF(K13="Non-Compliant",1,"")))
A14: GRA-2 | B14: CISO Designation & Authority | C14: Board reporting & engagement | D14: 1. Review board or board committee minutes from the last 4 quarters to verify the CISO presented or reported to the board on technology and cybersecurity risk. 2. Confirm the board meeting records document substantive discussion, questions raised, and actions taken in response to CISO reporting. 3. Verify the CISO has a standing agenda slot at the board risk committee or equivalent. 4. Assess the quality and comprehensiveness of CISO board reports — they should cover risk posture, incidents, compliance, emerging threats, and strategic security initiatives. | E14: Board/committee minutes documenting CISO presentations (last 4 quarters); CISO board reports or presentation materials; Board risk committee agenda showing CISO standing item; Records of board actions or directives arising from CISO reporting | F14: Inspection | M14: =IF(K14="Compliant",3,IF(K14="Partially Compliant",2,IF(K14="Non-Compliant",1,"")))
A15: GRA-2 | B15: CISO Designation & Authority | C15: Resources & budget adequacy | D15: 1. Obtain the security team structure and headcount under the CISO's authority. 2. Review the approved security budget for the current financial year and compare against industry benchmarks for capital market intermediaries. 3. Interview the CISO to assess whether resource constraints limit the ability to discharge responsibilities effectively. 4. Verify that the CISO has authority to approve security expenditure within the approved budget without requiring CTO sign-off. | E15: Security team organisational chart and headcount; Approved security budget for current year; CISO budget authority documentation; CISO interview notes on resource adequacy | F15: Inspection / Inquiry | M15: =IF(K15="Compliant",3,IF(K15="Partially Compliant",2,IF(K15="Non-Compliant",1,"")))
A16: GRA-2 | B16: CISO Designation & Authority | C16: CISO authority in practice | D16: 1. Review 3 instances (per sampling methodology) where the CISO exercised authority to influence technology decisions (e.g., halting a deployment, requiring security controls, rejecting a vendor). 2. Determine whether the CISO has the authority to halt a technology deployment if security risks are deemed unacceptable. 3. Verify that the CISO's role and authority are communicated to all relevant stakeholders including technology, trading, and business unit heads. 4. Assess whether the CISO participates in strategic technology decisions such as new system selection, cloud adoption, and algorithmic trading platform changes. | E16: Records of CISO-influenced technology decisions (3 instances); CISO authority policy or terms of reference; Evidence of CISO participation in strategic technology decision forums; Communication records notifying stakeholders of CISO authority | F16: Inspection / Inquiry | M16: =IF(K16="Compliant",3,IF(K16="Partially Compliant",2,IF(K16="Non-Compliant",1,"")))
A17: GRA-3 — Technology Risk Policy Suite
A18: PURPOSE: SC-GL/6-2023 requires capital market intermediaries to maintain a comprehensive suite of technology risk policies covering all guideline domains. This ensures that governance expectations are translated into enforceable standards that guide day-to-day operations across cybersecurity, data management, access control, and change management. EXPECTATION: The assessor should find a complete, board-approved policy suite that maps to all SC-GL/6-2023 domains, with each policy reviewed within 12 months, communicated to relevant personnel, and containing capital market-specific provisions. Policies should be enforceable with measurable standards rather than aspirational statements. KEY RISK: An incomplete or outdated policy suite creates ambiguity in expected controls, leaves staff without clear guidance on capital market-specific requirements, and exposes the intermediary to regulatory findings for non-compliance with SC-GL/6-2023 documentation expectations.
A19: GRA-3 | B19: Technology Risk Policy Suite | C19: Policy inventory & SC-GL/6-2023 coverage | D19: 1. Obtain the complete technology risk policy inventory listing all current policies. 2. Map the policy inventory against SC-GL/6-2023 domain requirements to verify coverage of: cybersecurity, technology risk assessment, data management, cloud services, third-party risk, incident management, business continuity, and technology audit. 3. Identify any domains where no corresponding policy exists and assess the entity's plan to address gaps. 4. Verify that each policy explicitly references the SC-GL/6-2023 requirements it addresses. | E19: Technology risk policy inventory or register; SC-GL/6-2023 domain coverage mapping; Gap analysis (if gaps identified); Sample policies showing SC-GL/6-2023 references | F19: Inspection | M19: =IF(K19="Compliant",3,IF(K19="Partially Compliant",2,IF(K19="Non-Compliant",1,"")))
A20: GRA-3 | B20: Technology Risk Policy Suite | C20: Board approval & review cycle | D20: 1. For each policy in the suite, verify board approval evidence (signature, board resolution, or minutes recording approval). 2. Confirm the last review date for each policy is within 12 months. 3. Review the policy review schedule and verify it is maintained and adhered to. 4. Determine whether policies have been updated to reflect recent SC advisories, regulatory changes, or significant incidents in the last 12 months. | E20: Board approval records for each policy (signatures, resolutions, or minutes); Policy review schedule; Policy version history showing last review dates; Records of policy updates following regulatory changes | F20: Inspection | M20: =IF(K20="Compliant",3,IF(K20="Partially Compliant",2,IF(K20="Non-Compliant",1,"")))
A21: GRA-3 | B21: Technology Risk Policy Suite | C21: Cybersecurity policy | D21: 1. Obtain the cybersecurity policy and verify it covers: threat management, security monitoring, vulnerability management, network security, endpoint protection, and security awareness. 2. Confirm the policy addresses capital market-specific cybersecurity requirements including protection of trading systems, market data integrity, and client portal security. 3. Verify the policy defines roles and responsibilities for cybersecurity across the three lines of defence. 4. Assess whether the policy establishes measurable security standards (e.g., patching SLAs, monitoring coverage targets, incident response timelines). | E21: Board-approved cybersecurity policy; Policy sections addressing capital market-specific requirements; Cybersecurity RACI matrix; Defined security standards and SLAs within the policy | F21: Inspection | M21: =IF(K21="Compliant",3,IF(K21="Partially Compliant",2,IF(K21="Non-Compliant",1,"")))
A22: GRA-3 | B22: Technology Risk Policy Suite | C22: Access control policy | D22: 1. Obtain the access control policy and verify it covers: user provisioning and de-provisioning, role-based access, privileged access management, multi-factor authentication, and periodic access reviews. 2. Confirm the policy mandates least-privilege access for all capital market systems including trading platforms, settlement systems, and client data repositories. 3. Verify that the policy addresses access control requirements for remote access, vendor access, and emergency access scenarios. 4. Review whether the policy defines access review frequency (at least quarterly for privileged access, at least annually for standard access). | E22: Board-approved access control policy; Policy sections on privileged access and MFA requirements; Access review frequency requirements; Remote and vendor access control provisions | F22: Inspection | M22: =IF(K22="Compliant",3,IF(K22="Partially Compliant",2,IF(K22="Non-Compliant",1,"")))
A23: GRA-3 | B23: Technology Risk Policy Suite | C23: Data security & privacy policy | D23: 1. Obtain the data security and privacy policy and verify it covers: data classification, encryption standards, data loss prevention, data retention, and disposal. 2. Confirm the policy addresses PDPA compliance requirements for client personal data held by the capital market intermediary. 3. Verify the policy defines data handling requirements specific to market data, client trading information, and corporate confidential data. 4. Assess whether the policy establishes encryption standards (AES-256 at rest, TLS 1.2+ in transit) and data residency requirements consistent with SC and PDPA expectations. | E23: Board-approved data security and privacy policy; PDPA compliance provisions within the policy; Data classification scheme referenced by the policy; Encryption and data residency standards defined in the policy | F23: Inspection | M23: =IF(K23="Compliant",3,IF(K23="Partially Compliant",2,IF(K23="Non-Compliant",1,"")))
A24: GRA-3 | B24: Technology Risk Policy Suite | C24: Change management policy | D24: 1. Obtain the change management policy and verify it defines: change classification (critical, significant, standard), risk assessment requirements, testing and approval gates, and rollback procedures. 2. Confirm the policy addresses change freeze periods around critical market events (e.g., settlement cycles, quarter-end, market launches). 3. Verify the policy establishes special controls for changes to trading systems, settlement systems, and market connectivity. 4. Assess whether the policy defines emergency change procedures with retrospective risk assessment and approval requirements. | E24: Board-approved change management policy; Change classification criteria; Change freeze period definitions; Emergency change procedures; Special controls for trading system changes | F24: Inspection | M24: =IF(K24="Compliant",3,IF(K24="Partially Compliant",2,IF(K24="Non-Compliant",1,"")))
A25: GRA-3 | B25: Technology Risk Policy Suite | C25: Additional policy areas (BCP, cloud, outsourcing, incident management) | D25: 1. Verify that policies exist for: business continuity and disaster recovery, cloud services governance, technology outsourcing, and incident management and response. 2. For each, confirm board approval and review within the last 12 months. 3. Assess whether each policy is aligned with the corresponding SC-GL/6-2023 domain requirements and references the guideline. 4. Review a sample of 3 additional policies (per sampling methodology) in detail for adequacy of content, clarity of responsibilities, and enforceability. | E25: BCP/DR policy (board-approved); Cloud services policy (board-approved); Technology outsourcing policy (board-approved); Incident management policy (board-approved); Board approval and review date evidence for each | F25: Inspection | M25: =IF(K25="Compliant",3,IF(K25="Partially Compliant",2,IF(K25="Non-Compliant",1,"")))
A26: GRA-3 | B26: Technology Risk Policy Suite | C26: Policy communication & awareness | D26: 1. Inspect evidence of policy communication to all relevant personnel (e.g., intranet publication, email distribution, training records, acknowledgement logs). 2. Review policy acknowledgement records to verify staff have confirmed receipt and understanding. 3. Interview 3 staff from different functions (per sampling methodology) (e.g., trading, operations, IT) to verify awareness and ability to locate key technology risk policies. 4. Verify that policy communication extends to relevant third-party service providers where contractually required. | E26: Policy distribution records or intranet publication evidence; Staff acknowledgement logs; Training completion records for policy awareness; Third-party policy communication records; Interview notes from 3 staff across functions | F26: Inspection / Inquiry | M26: =IF(K26="Compliant",3,IF(K26="Partially Compliant",2,IF(K26="Non-Compliant",1,"")))
A27: GRA-4 — Technology Risk Reporting
A28: PURPOSE: SC-GL/6-2023 requires capital market intermediaries to provide regular, comprehensive technology risk reporting to the board and senior management. This ensures informed decision-making on technology risks that could impact market operations, client protection, and regulatory compliance. EXPECTATION: The assessor should find a consistent quarterly reporting cadence with reports covering all SC-GL/6-2023 domains, defined KRIs with escalation thresholds, emerging risk commentary, and audit remediation tracking. Board minutes should evidence substantive engagement with the reports, not just receipt. KEY RISK: Inadequate risk reporting leaves the board unable to exercise effective oversight, meaning material technology risks affecting trading systems, client data, or market integrity may persist without senior management awareness or intervention.
A29: GRA-4 | B29: Technology Risk Reporting | C29: Reporting cadence & completeness | D29: 1. Obtain technology risk reports submitted to the board or board committee for the last 4 quarters. 2. Verify a consistent quarterly (or more frequent) reporting cadence with no gaps. 3. Review report content for inclusion of: key risk indicators, incident trends, compliance metrics, audit remediation status, and emerging technology risk commentary. 4. Confirm reports cover all SC-GL/6-2023 domains and are not limited to cybersecurity incidents alone. | E29: Technology risk reports (last 4 quarters); Board committee agenda confirming standing reporting item; Report content checklist or template; Reports covering all GTRM domains | F29: Inspection | M29: =IF(K29="Compliant",3,IF(K29="Partially Compliant",2,IF(K29="Non-Compliant",1,"")))
A30: GRA-4 | B30: Technology Risk Reporting | C30: Key Risk Indicators & thresholds | D30: 1. Obtain the documented KRI definitions and thresholds for technology risk. 2. Verify that KRIs cover capital market-specific risk dimensions: trading system availability, settlement failure rates, cybersecurity incident counts, patch compliance, and vendor SLA performance. 3. Confirm escalation triggers are defined for threshold breaches and review evidence that breaches have been escalated in practice. 4. Assess whether KRI thresholds are calibrated periodically (at least annually) and reviewed for continued appropriateness. | E30: KRI definitions and threshold document; Evidence of threshold breach escalation (last 12 months); KRI calibration review records; Capital market-specific KRI examples (system availability, settlement failure rate) | F30: Inspection | M30: =IF(K30="Compliant",3,IF(K30="Partially Compliant",2,IF(K30="Non-Compliant",1,"")))
A31: GRA-4 | B31: Technology Risk Reporting | C31: Board engagement with risk reports | D31: 1. Review board or board committee minutes from the last 4 quarters to confirm discussion of technology risk reports. 2. Verify that minutes record board questions, challenges, and decisions taken in response to risk reporting. 3. Confirm that board directives or action items arising from risk reporting are tracked to completion. 4. Assess whether the board has requested deeper analysis or additional reporting on specific risk areas in the last 12 months. | E31: Board/committee minutes documenting risk report discussion (last 4 quarters); Board action items arising from risk reports; Evidence of board-requested deep-dive analyses; Board directive tracking log | F31: Inspection | M31: =IF(K31="Compliant",3,IF(K31="Partially Compliant",2,IF(K31="Non-Compliant",1,"")))
A32: GRA-4 | B32: Technology Risk Reporting | C32: Emerging risk identification & reporting | D32: 1. Review the last 4 quarterly reports for inclusion of emerging technology risk commentary. 2. Verify that emerging risks reported are relevant to capital market operations (e.g., AI/ML risks in algorithmic trading, quantum computing threats, supply chain attacks, new SC regulatory requirements). 3. Confirm the entity has a process for identifying emerging risks through horizon scanning, industry intelligence, and SC advisory monitoring. 4. Interview the CISO or CRO to understand how emerging risks are identified, assessed, and prioritised for board reporting. | E32: Emerging risk sections from quarterly reports; Horizon scanning or emerging risk identification process documentation; SC advisory monitoring log; CISO/CRO interview notes on emerging risk process | F32: Inspection / Inquiry | M32: =IF(K32="Compliant",3,IF(K32="Partially Compliant",2,IF(K32="Non-Compliant",1,"")))
A33: GRA-4 | B33: Technology Risk Reporting | C33: Audit finding remediation reporting | D33: 1. Verify that technology risk reports include the status of audit finding remediation. 2. Review the remediation tracking section of the most recent 2 quarterly reports for accuracy — cross-check against the audit findings tracker. 3. Confirm that overdue findings are highlighted and escalated to the board with owner accountability. 4. Assess whether the board has visibility over the ageing profile of open audit findings and trend over time. | E33: Audit remediation status sections from quarterly reports (last 2 quarters); Audit findings tracker for cross-reference; Board escalation records for overdue findings; Ageing profile of open findings | F33: Inspection | M33: =IF(K33="Compliant",3,IF(K33="Partially Compliant",2,IF(K33="Non-Compliant",1,"")))
A34: GRA-5 — Technology Risk Assessment Framework
A35: PURPOSE: SC-GL/6-2023 requires capital market intermediaries to maintain a structured technology risk assessment framework that identifies, assesses, and treats technology risks across all capital market operations. This ensures risks are systematically managed rather than addressed ad hoc. EXPECTATION: The assessor should find a documented risk assessment methodology with capital market-specific risk categories, a current risk register with assigned owners and treatment plans, annual comprehensive assessments completed within 12 months, and integration with the enterprise risk management framework. Out-of-cycle assessment triggers should be defined for material changes. KEY RISK: Without a structured risk assessment framework, technology risks affecting trading systems, settlement infrastructure, and market data integrity may be unidentified or underestimated, leading to inadequate controls and potential market disruption.
A36: GRA-5 | B36: Technology Risk Assessment Framework | C36: Risk assessment methodology | D36: 1. Obtain the technology risk assessment methodology document. 2. Verify it defines risk identification approaches, likelihood and impact assessment criteria, risk rating scales, and treatment options aligned with SC-GL/6-2023. 3. Confirm the methodology addresses capital market-specific risk categories including trading system failure, settlement disruption, market data corruption, and client data breach. 4. Assess whether the methodology is consistent with the entity's enterprise risk management framework. | E36: Technology risk assessment methodology document; Risk rating scales and criteria; Capital market-specific risk category definitions; ERM framework alignment mapping | F36: Inspection | M36: =IF(K36="Compliant",3,IF(K36="Partially Compliant",2,IF(K36="Non-Compliant",1,"")))
A37: GRA-5 | B37: Technology Risk Assessment Framework | C37: Annual comprehensive risk assessment | D37: 1. Obtain the most recent annual technology risk assessment report. 2. Verify the assessment covers all capital market technology domains: trading systems, settlement and clearing infrastructure, market data systems, client portals, and supporting IT infrastructure. 3. Confirm the assessment identifies specific risks, assigns risk ratings, and documents treatment decisions with assigned owners. 4. Verify the assessment was completed within the last 12 months and results were presented to senior management and the board. | E37: Annual technology risk assessment report (last 12 months); Risk register extract showing identified risks, ratings, and owners; Board or senior management presentation of assessment results; Assessment scope documentation covering all capital market domains | F37: Inspection | M37: =IF(K37="Compliant",3,IF(K37="Partially Compliant",2,IF(K37="Non-Compliant",1,"")))
A38: GRA-5 | B38: Technology Risk Assessment Framework | C38: Risk treatment & tracking | D38: 1. Select a sample of 5 high-rated technology risks from the risk register (per sampling methodology). 2. For each, trace through to the treatment plan and verify it documents: treatment approach (mitigate, accept, transfer, avoid), specific actions, responsible owner, target date, and current status. 3. Confirm that risk acceptances are approved at the appropriate level of authority and documented with compensating controls where applicable. 4. Verify that the risk register is maintained as a living document with regular updates — not only updated at annual assessment time. | E38: Risk register with treatment plans (sample of 5 high-rated risks per sampling methodology); Risk acceptance approvals with authority evidence; Treatment action tracking log; Risk register update history showing regular maintenance | F38: Inspection | M38: =IF(K38="Compliant",3,IF(K38="Partially Compliant",2,IF(K38="Non-Compliant",1,"")))
A39: GRA-5 | B39: Technology Risk Assessment Framework | C39: ERM integration | D39: 1. Interview the CRO or risk management team to understand how technology risk assessment results feed into the enterprise risk register and risk appetite monitoring. 2. Verify that technology risks are represented in the enterprise risk register at an appropriate level of granularity. 3. Confirm that technology risk assessments use consistent scales and terminology with the enterprise risk framework to enable comparison. 4. Assess whether technology risk reporting to the board is integrated with enterprise risk reporting or delivered as a separate, disconnected stream. | E39: Enterprise risk register showing technology risk entries; ERM framework referencing technology risk integration; CRO/risk team interview notes; Board risk report showing integrated technology and enterprise risk view | F39: Inspection / Inquiry | M39: =IF(K39="Compliant",3,IF(K39="Partially Compliant",2,IF(K39="Non-Compliant",1,"")))
A40: GRA-5 | B40: Technology Risk Assessment Framework | C40: Out-of-cycle risk assessment triggers | D40: 1. Verify that documented triggers exist for conducting out-of-cycle technology risk assessments (e.g., major system changes, significant incidents, new SC guidance, material market events). 2. Review whether any out-of-cycle assessments have been conducted in the last 12 months and assess their adequacy. 3. Confirm that the trigger criteria are aligned with capital market operating conditions, including triggers related to Bursa Malaysia system changes, new trading products, and regulatory changes. 4. Interview the risk team to understand how ad-hoc risk assessments are initiated and whether the process is responsive enough for fast-moving market conditions. | E40: Out-of-cycle assessment trigger criteria documentation; Records of out-of-cycle assessments conducted (last 12 months, if any); Risk team interview notes on trigger responsiveness; Trigger criteria referencing capital market events | F40: Inspection / Inquiry | M40: =IF(K40="Compliant",3,IF(K40="Partially Compliant",2,IF(K40="Non-Compliant",1,"")))
A41: GRA-6 — Algorithmic Trading Risk Controls
A42: PURPOSE: SC-GL/6-2023 requires capital market intermediaries using algorithmic trading to implement robust pre-trade and post-trade risk controls to prevent market disruption and manipulation. This control ensures that algorithmic trading activity is conducted within defined risk parameters with effective kill switch and surveillance capabilities. EXPECTATION: The assessor should find documented pre-trade risk controls (price limits, order size limits, position limits) actively configured and calibrated, a tested kill switch capability, a formal algorithm approval process with compliance sign-off, and post-trade surveillance monitoring for market manipulation patterns. Periodic reviews and recalibration should be evidenced. KEY RISK: Inadequate algorithmic trading controls can result in errant orders, market manipulation, or runaway algorithms that disrupt Bursa Malaysia market operations, triggering regulatory action from the SC and potential financial losses to clients and the intermediary.
A43: GRA-6 | B43: Algorithmic Trading Risk Controls | C43: Pre-trade risk controls | D43: 1. Obtain documentation of all pre-trade risk controls configured in the algorithmic trading system (price limits, order size limits, position limits, daily loss limits, message throttling). 2. Verify that pre-trade control thresholds are calibrated to current market conditions and the entity's risk appetite — not set at default or stale values. 3. Inspect the trading system configuration to confirm pre-trade controls are active and cannot be bypassed without authorised override and logging. 4. Review records from the last quarter of any pre-trade control triggers or breaches, confirming each was detected, logged, and investigated. | E43: Pre-trade risk control configuration documentation; Trading system screenshots or configuration exports showing active controls; Threshold calibration records and approval; Pre-trade control trigger/breach log (last quarter) | F43: Inspection | M43: =IF(K43="Compliant",3,IF(K43="Partially Compliant",2,IF(K43="Non-Compliant",1,"")))
A44: GRA-6 | B44: Algorithmic Trading Risk Controls | C44: Kill switch capability | D44: 1. Request a demonstration or documented evidence of the kill switch capability for halting all algorithmic trading activity. 2. Verify that the kill switch can halt all algorithmic orders within a defined timeframe (target: seconds, not minutes). 3. Confirm that authority to activate the kill switch is clearly defined and multiple authorised personnel can activate it during market hours. 4. Review kill switch test records from the last 12 months and verify testing was conducted in a realistic scenario (not just a documentation exercise). | E44: Kill switch documentation (design, activation procedure); Kill switch test records (last 12 months); List of authorised personnel for kill switch activation; Kill switch activation log (if any live activations); Test scenario description and results | F44: Inspection / Observation | M44: =IF(K44="Compliant",3,IF(K44="Partially Compliant",2,IF(K44="Non-Compliant",1,"")))
A45: GRA-6 | B45: Algorithmic Trading Risk Controls | C45: Algorithm testing & approval process | D45: 1. Obtain the algorithm testing and approval procedure document. 2. Select a sample of 3 recently deployed algorithms (per sampling methodology) and review the approval records including: risk assessment, compliance sign-off, and formal authorisation before production deployment. 3. For the same sample, verify testing evidence including backtesting results, simulation testing in a non-production environment, and stress testing under extreme market conditions. 4. Confirm that no algorithm was deployed to production without completing all required approval gates. 5. Interview the Head of Trading to understand how algorithm performance is monitored post-deployment and what triggers a review or suspension. | E45: Algorithm testing and approval procedure; Approval records for 3 recently deployed algorithms (per sampling methodology); Backtesting and simulation test results; Stress test results under extreme market conditions; Compliance sign-off records; Head of Trading interview notes | F45: Inspection / Inquiry | M45: =IF(K45="Compliant",3,IF(K45="Partially Compliant",2,IF(K45="Non-Compliant",1,"")))
A46: GRA-6 | B46: Algorithmic Trading Risk Controls | C46: Post-trade surveillance & market manipulation monitoring | D46: 1. Inspect post-trade surveillance reports for the last 3 months (per sampling methodology) to verify monitoring for market manipulation patterns in algorithmic activity (spoofing, layering, wash trading, momentum ignition). 2. Verify that surveillance rules are calibrated to detect manipulation patterns specific to the entity's algorithmic trading strategies and the instruments traded on Bursa Malaysia. 3. Review a sample of 5 surveillance alerts (per sampling methodology) and confirm each was investigated, documented, and resolved appropriately. 4. Assess whether post-trade surveillance findings are reported to Compliance and, where required, escalated to SC or Bursa Malaysia. | E46: Post-trade surveillance reports (last 3 months); Surveillance rule definitions for market manipulation detection; Sample alert investigation records (5 alerts per sampling methodology); Escalation records to Compliance, SC, or Bursa (if applicable) | F46: Inspection | M46: =IF(K46="Compliant",3,IF(K46="Partially Compliant",2,IF(K46="Non-Compliant",1,"")))
A47: GRA-6 | B47: Algorithmic Trading Risk Controls | C47: Limit breach response & escalation | D47: 1. Review the documented escalation procedure for pre-trade limit breaches and post-trade surveillance alerts during market hours. 2. Obtain records of any limit breaches or kill switch activations in the last 12 months. 3. For each breach event, verify appropriate investigation was conducted, root cause identified, and follow-up actions taken to prevent recurrence. 4. Interview the risk controls team to understand how limit breaches are detected and escalated in real-time during market hours, including communication between trading desk, risk, and compliance. | E47: Limit breach escalation procedure; Breach event records (last 12 months); Investigation and root cause analysis reports for breaches; Risk controls team interview notes; Communication logs between trading, risk, and compliance during breach events | F47: Inspection / Inquiry | M47: =IF(K47="Compliant",3,IF(K47="Partially Compliant",2,IF(K47="Non-Compliant",1,"")))
A48: GRA-6 | B48: Algorithmic Trading Risk Controls | C48: Periodic algorithm review & recalibration | D48: 1. Obtain records of periodic reviews conducted for existing production algorithms (at minimum annually). 2. Verify that reviews assess continued appropriateness, performance against expectations, and risk profile under current market conditions. 3. Confirm that pre-trade control thresholds and position limits are recalibrated based on changed market conditions, volumes, and volatility. 4. Review any instances where an algorithm was suspended or retired following periodic review and verify the decision was documented and approved. | E48: Periodic algorithm review records (last 12 months); Threshold recalibration records; Algorithm suspension or retirement decisions (if any); Review approval records signed by Head of Trading and Compliance | F48: Inspection | M48: =IF(K48="Compliant",3,IF(K48="Partially Compliant",2,IF(K48="Non-Compliant",1,"")))
A49: GRA-7 — Technology Change Risk Assessment
A50: PURPOSE: SC-GL/6-2023 requires capital market intermediaries to conduct risk assessments for technology changes before production deployment, with heightened controls for changes to trading and settlement systems. This ensures that changes do not introduce unacceptable risks to market operations or client services. EXPECTATION: The assessor should find a change management process with defined risk classification tiers, documented risk assessments for critical changes, appropriate testing and approval gates, rollback procedures accounting for market hours, and controlled emergency change processes. Change freeze policies during trading hours should be evidenced. KEY RISK: Inadequate change risk assessment can lead to production failures in trading or settlement systems during market hours, causing trade execution failures, settlement delays, or data integrity issues that harm clients and attract regulatory scrutiny.
A51: GRA-7 | B51: Technology Change Risk Assessment | C51: Change classification & risk assessment | D51: 1. Obtain the change management policy and verify it defines change risk classification criteria (critical, significant, standard) with corresponding risk assessment and approval requirements for each tier. 2. Select a sample of 5 recent changes to critical trading or settlement systems (per sampling methodology). 3. For each, verify a documented risk assessment was completed before production deployment that considers impact on trading operations, settlement processing, and client services. 4. Confirm that risk assessment findings informed the testing approach and approval requirements applied to each change. | E51: Change management policy with classification criteria; Change records for 5 critical/significant changes (per sampling methodology); Risk assessment documentation for each sampled change; Evidence linking risk assessment outcomes to testing and approval requirements | F51: Inspection | M51: =IF(K51="Compliant",3,IF(K51="Partially Compliant",2,IF(K51="Non-Compliant",1,"")))
A52: GRA-7 | B52: Technology Change Risk Assessment | C52: Testing & approval gates | D52: 1. For the same sample of 5 changes (per sampling methodology), verify that each completed required testing in a non-production environment before deployment. 2. Confirm that appropriate approval was obtained at each gate, with approvers having sufficient authority and independence from the change requestor. 3. Verify that user acceptance testing (UAT) was conducted and signed off by the business owner for changes affecting trading or settlement functionality. 4. Assess whether testing covered regression, performance, and security aspects in addition to functional testing. | E52: Test plans and results for sampled changes; Approval records with approver names and authority; UAT sign-off records from business owners; Evidence of regression, performance, and security testing | F52: Inspection | M52: =IF(K52="Compliant",3,IF(K52="Partially Compliant",2,IF(K52="Non-Compliant",1,"")))
A53: GRA-7 | B53: Technology Change Risk Assessment | C53: Rollback procedures & post-implementation review | D53: 1. For the same sample of 5 changes (per sampling methodology), verify that rollback procedures were defined before deployment and are specific enough to be executed if the change fails. 2. Confirm that post-implementation reviews were conducted to verify the change met objectives and no adverse impacts occurred. 3. Assess whether rollback procedures for trading system changes account for market operating hours and the need to restore service before the next trading session. 4. Review any instances where a rollback was actually executed in the last 12 months and verify the rollback process worked as designed. | E53: Rollback procedure documentation for sampled changes; Post-implementation review records; Rollback execution records (if any, last 12 months); Market hours considerations in rollback procedures for trading systems | F53: Inspection | M53: =IF(K53="Compliant",3,IF(K53="Partially Compliant",2,IF(K53="Non-Compliant",1,"")))
A54: GRA-7 | B54: Technology Change Risk Assessment | C54: Emergency change controls | D54: 1. Review the change log for the last quarter and identify all changes classified as emergency. 2. Calculate the emergency change ratio and assess whether it indicates potential process bypass (red flag: >15% emergency changes). 3. For each emergency change identified, verify retrospective risk assessment and approval was completed within the defined timeframe. 4. Confirm that emergency changes to trading systems during market hours followed specific protocols including real-time risk monitoring and defined rollback triggers. | E54: Change log for last quarter with emergency change identification; Emergency change ratio calculation; Retrospective approval records for emergency changes; Trading-hours emergency change protocols | F54: Inspection | M54: =IF(K54="Compliant",3,IF(K54="Partially Compliant",2,IF(K54="Non-Compliant",1,"")))
A55: GRA-7 | B55: Technology Change Risk Assessment | C55: Market hours coordination | D55: 1. Interview the change manager to understand how changes to trading and settlement systems are scheduled relative to Bursa Malaysia market operating hours. 2. Verify that a change freeze policy exists prohibiting non-emergency changes to trading systems during market hours and around critical market events (settlement cycles, quarter-end, IPO launches). 3. Review the change schedule for the last quarter to confirm compliance with the change freeze policy. 4. Assess how the entity coordinates changes to market connectivity systems with Bursa Malaysia, clearing houses, and depository schedule windows. | E55: Change freeze policy for market hours; Change schedule (last quarter) showing compliance with freeze windows; Change manager interview notes on market hours coordination; Coordination records with Bursa Malaysia for connectivity changes | F55: Inspection / Inquiry | M55: =IF(K55="Compliant",3,IF(K55="Partially Compliant",2,IF(K55="Non-Compliant",1,"")))
A56: GRA-8 — Technology Audit Programme
A57: PURPOSE: SC-GL/6-2023 requires capital market intermediaries to maintain a technology audit programme providing independent assurance over technology risk management. This ensures that controls are independently validated, deficiencies are identified, and remediation is tracked to closure. EXPECTATION: The assessor should find a risk-based audit plan covering all SC-GL/6-2023 domains over the audit cycle, qualified and independent auditors, quality audit reports with actionable findings, regular audit committee reporting, and a findings remediation tracker with validated closures. High-risk areas like trading systems and algorithmic trading should be prioritised. KEY RISK: Without an effective technology audit programme, control weaknesses in trading systems, cybersecurity, and third-party arrangements may persist undetected, increasing the risk of operational failures and undermining the intermediary's ability to demonstrate compliance to the SC.
A58: GRA-8 | B58: Technology Audit Programme | C58: Risk-based audit plan | D58: 1. Obtain the current technology audit plan and verify it is risk-based, covering all SC-GL/6-2023 domains over the audit cycle. 2. Confirm the audit plan defines scope, timing, resource requirements, and audit methodology for each planned engagement. 3. Verify that the audit plan prioritises high-risk areas including trading systems, algorithmic trading controls, cybersecurity, and third-party risk management. 4. Assess whether the audit plan is reviewed and refreshed at least annually or when the risk profile materially changes. | E58: Current technology audit plan; Risk-based prioritisation methodology; SC-GL/6-2023 domain coverage mapping for the audit cycle; Audit plan approval by the audit committee | F58: Inspection | M58: =IF(K58="Compliant",3,IF(K58="Partially Compliant",2,IF(K58="Non-Compliant",1,"")))
A59: GRA-8 | B59: Technology Audit Programme | C59: Auditor qualifications & independence | D59: 1. Review the qualifications and experience of technology auditors (internal or external) assigned to the programme. 2. Verify auditors hold relevant certifications (e.g., CISA, CISSP, CRISC) and have experience with capital market technology environments. 3. Confirm auditor independence — technology auditors should not have operational responsibilities for the systems they audit. 4. Where external auditors are engaged, verify the selection process considered capital market industry experience and the firm's independence. | E59: Auditor profiles with qualifications and certifications; Independence declarations; Capital market experience evidence; External auditor selection documentation (if applicable) | F59: Inspection | M59: =IF(K59="Compliant",3,IF(K59="Partially Compliant",2,IF(K59="Non-Compliant",1,"")))
A60: GRA-8 | B60: Technology Audit Programme | C60: Audit execution & report quality | D60: 1. Review 3 completed technology audit reports from the last 12 months (per sampling methodology). 2. Verify reports contain: clear scope, methodology, detailed findings with risk ratings, root cause analysis, and actionable recommendations. 3. Assess whether audit findings are specific enough to drive remediation — not generic observations that lack actionable detail. 4. Confirm that audit reports reflect capital market-specific risks and controls, not generic IT audit checklists. | E60: Completed technology audit reports (3, last 12 months per sampling methodology); Audit methodology documentation; Sample findings with risk ratings and recommendations; Evidence of capital market-specific audit scope | F60: Inspection | M60: =IF(K60="Compliant",3,IF(K60="Partially Compliant",2,IF(K60="Non-Compliant",1,"")))
A61: GRA-8 | B61: Technology Audit Programme | C61: Audit committee reporting | D61: 1. Review audit committee minutes from the last 2 meetings to verify technology audit findings are reported and discussed. 2. Confirm the audit committee receives adequate information: finding summaries, risk ratings, management responses, and remediation timelines. 3. Verify that the audit committee has challenged management on overdue findings and remediation progress. 4. Assess whether the audit committee has directed additional audit coverage for emerging risk areas such as algorithmic trading, AI/ML, or cloud services. | E61: Audit committee minutes (last 2 meetings); Technology audit presentation materials to audit committee; Audit committee directive records; Management response records presented to audit committee | F61: Inspection | M61: =IF(K61="Compliant",3,IF(K61="Partially Compliant",2,IF(K61="Non-Compliant",1,"")))
A62: GRA-8 | B62: Technology Audit Programme | C62: Findings remediation tracking | D62: 1. Obtain the audit findings remediation tracker. 2. Select a sample of 10 findings (per sampling methodology) and verify each is assigned to an owner, has a target remediation date, and is tracked through to closure. 3. Calculate the percentage of findings currently overdue and assess the ageing profile. 4. Verify that overdue findings are escalated to senior management and the audit committee with clear accountability. 5. Confirm that remediated findings are validated (re-tested or evidence reviewed) before closure — not simply closed on management assertion. | E62: Audit findings remediation tracker; Sample of 10 findings (per sampling methodology) with owner, target date, and status; Overdue findings escalation records; Remediation validation evidence for closed findings | F62: Inspection | M62: =IF(K62="Compliant",3,IF(K62="Partially Compliant",2,IF(K62="Non-Compliant",1,"")))
A63: GRA-9 — Regulatory Examination Readiness
A64: PURPOSE: SC-GL/6-2023 expects capital market intermediaries to be prepared for regulatory examination at any time, maintaining current evidence and demonstrating continuous compliance rather than reactive preparation. This control ensures the entity can respond efficiently to SC examination requests and demonstrate an ongoing compliance posture. EXPECTATION: The assessor should find a maintained evidence library mapped to SC-GL/6-2023 requirements with current documentation, a self-assessment completed within 12 months, a designated examination response team with tested protocols, tracked remediation of prior examination findings, and evidence of continuous compliance monitoring. KEY RISK: Poor examination readiness results in delayed and incomplete responses to SC examinations, increasing the risk of adverse regulatory findings, enforcement action, and reputational damage in the capital market.
A65: GRA-9 | B65: Regulatory Examination Readiness | C65: Evidence library & currency | D65: 1. Verify that a standing evidence library is maintained mapping evidence items to SC-GL/6-2023 requirements. 2. Assess the currency of evidence items — confirm that governance documents, reports, test results, and meeting minutes are within their defined refresh periods (e.g., policies within 12 months, minutes within current quarter). 3. Identify any evidence gaps where required documentation does not exist or is stale. 4. Verify that the evidence library is centrally managed with designated custodians responsible for keeping items current. | E65: Evidence library index mapped to SC-GL/6-2023 requirements; Evidence currency assessment results; Evidence custodian assignments; Evidence gap list (if any) | F65: Inspection | M65: =IF(K65="Compliant",3,IF(K65="Partially Compliant",2,IF(K65="Non-Compliant",1,"")))
A66: GRA-9 | B66: Regulatory Examination Readiness | C66: Self-assessment against SC-GL/6-2023 | D66: 1. Obtain the most recent self-assessment against SC-GL/6-2023 guidelines. 2. Verify the self-assessment covers all guideline requirements with an honest assessment of compliance status (fully compliant, partially compliant, non-compliant). 3. Confirm that gaps identified in the self-assessment have remediation plans with assigned owners and target dates. 4. Assess the self-assessment methodology — verify it goes beyond documentation review to include testing of control effectiveness. 5. Confirm the self-assessment was conducted within the last 12 months. | E66: Self-assessment report against SC-GL/6-2023; Self-assessment methodology document; Gap remediation plan with owners and target dates; Self-assessment completion date evidence | F66: Inspection | M66: =IF(K66="Compliant",3,IF(K66="Partially Compliant",2,IF(K66="Non-Compliant",1,"")))
A67: GRA-9 | B67: Regulatory Examination Readiness | C67: Examination response team & protocols | D67: 1. Review the examination response team composition and verify it includes designated contact persons from compliance, CISO function, IT, and business units. 2. Verify that examination response protocols exist covering: document production procedures, interview coordination, information request management, and confidentiality handling. 3. Confirm contact details for the response team are current and the team has conducted at least one readiness exercise in the last 12 months. 4. Assess whether the entity can produce evidence for all SC-GL/6-2023 requirements within the expected regulatory examination response timeline. | E67: Examination response team roster with roles and contact details; Examination response protocol document; Readiness exercise records (last 12 months); Evidence production timeline assessment | F67: Inspection / Inquiry | M67: =IF(K67="Compliant",3,IF(K67="Partially Compliant",2,IF(K67="Non-Compliant",1,"")))
A68: GRA-9 | B68: Regulatory Examination Readiness | C68: Prior examination finding remediation | D68: 1. Obtain the tracker for prior SC examination findings (if any examinations have been conducted). 2. Verify that all findings from the most recent examination have been assigned owners and remediation plans. 3. Confirm that remediated findings have evidence of closure and validation. 4. Identify any findings that remain open and assess whether they are being actively managed with the SC's expectations addressed. 5. Where no prior examination has occurred, verify the entity has proactively identified and addressed likely examination focus areas through self-assessment. | E68: Prior SC examination finding tracker; Remediation evidence for closed findings; Open finding management records; SC communication records regarding finding remediation (if applicable); Self-assessment as proxy if no prior examination | F68: Inspection | M68: =IF(K68="Compliant",3,IF(K68="Partially Compliant",2,IF(K68="Non-Compliant",1,"")))
A69: GRA-9 | B69: Regulatory Examination Readiness | C69: Continuous compliance monitoring | D69: 1. Assess whether the entity monitors compliance with SC-GL/6-2023 on an ongoing basis rather than only preparing for examinations. 2. Review evidence of regular compliance monitoring activities (e.g., quarterly compliance checks, automated control testing, exception reporting). 3. Verify that SC advisories, updates, and new guidance are tracked and assessed for impact on the entity's compliance posture. 4. Interview Compliance or the CISO to understand the process for maintaining compliance between formal self-assessments and how emerging regulatory changes are incorporated. | E69: Compliance monitoring schedule and records; SC advisory tracking log; Compliance exception reports (last 2 quarters); Compliance/CISO interview notes on ongoing monitoring approach | F69: Inspection / Inquiry | M69: =IF(K69="Compliant",3,IF(K69="Partially Compliant",2,IF(K69="Non-Compliant",1,"")))
A70: GRA-10 — Penetration Testing Programme
A71: PURPOSE: SC-GL/6-2023 requires capital market intermediaries to conduct regular penetration testing of their technology environment by qualified, independent testers. This provides an adversarial assessment of the security posture beyond what vulnerability scanning and self-assessment can reveal. EXPECTATION: The assessor should find annual penetration testing covering critical capital market systems (trading, settlement, client portals, exchange connectivity), conducted by qualified independent testers with capital market experience. Findings should be tracked with defined remediation SLAs, critical and high findings re-tested after remediation, and results reported to the board audit committee with trend analysis. KEY RISK: Without regular penetration testing, exploitable vulnerabilities in trading platforms, client-facing systems, and exchange connectivity may remain undetected, creating attack vectors for threat actors targeting capital market infrastructure.
A72: GRA-10 | B72: Penetration Testing Programme | C72: Testing scope & frequency | D72: 1. Obtain the penetration testing policy or terms of reference and verify it defines testing frequency (at minimum annually) and scope requirements. 2. Confirm the scope of the most recent penetration test covers critical capital market systems: trading platforms, client portals, market data interfaces, settlement system connectivity, and internet-facing applications. 3. Verify that the testing scope includes both external and internal testing perspectives. 4. Assess whether the scope addresses application-layer testing in addition to infrastructure testing, particularly for client-facing web and mobile platforms. | E72: Penetration testing policy or terms of reference; Most recent penetration test scope document; Scope coverage mapping against critical capital market systems; Evidence of external and internal testing perspectives | F72: Inspection | M72: =IF(K72="Compliant",3,IF(K72="Partially Compliant",2,IF(K72="Non-Compliant",1,"")))
A73: GRA-10 | B73: Penetration Testing Programme | C73: Tester qualifications & independence | D73: 1. Review the qualifications and certifications of penetration testers engaged (e.g., OSCP, CREST CRT, GPEN). 2. Verify that testers are independent from the entity — not employees or the same firm that implemented the systems being tested. 3. Confirm the selection process considered the testing firm's experience with capital market environments and regulated financial entities. 4. Review the engagement terms to verify they include appropriate confidentiality protections for market-sensitive information and client data encountered during testing. | E73: Penetration tester profiles with certifications; Independence verification (not the implementation vendor); Engagement terms with confidentiality provisions; Selection criteria including capital market experience | F73: Inspection | M73: =IF(K73="Compliant",3,IF(K73="Partially Compliant",2,IF(K73="Non-Compliant",1,"")))
A74: GRA-10 | B74: Penetration Testing Programme | C74: Findings remediation & re-testing | D74: 1. Obtain the penetration testing findings tracker from the most recent test. 2. Verify that critical and high findings have defined remediation SLAs and are being tracked to closure within those SLAs. 3. Confirm that remediated critical and high findings are re-tested by the penetration tester to verify effective resolution — not closed on management assertion alone. 4. Review any findings that exceeded the remediation SLA and assess whether appropriate risk acceptance was documented and approved at the right authority level. | E74: Penetration test findings tracker with SLAs; Remediation status for critical and high findings; Re-testing evidence from penetration tester confirming resolution; Risk acceptance records for overdue findings (if any) | F74: Inspection | M74: =IF(K74="Compliant",3,IF(K74="Partially Compliant",2,IF(K74="Non-Compliant",1,"")))
A75: GRA-10 | B75: Penetration Testing Programme | C75: Board reporting & trend analysis | D75: 1. Verify that penetration testing results are reported to the board audit committee. 2. Review the board reporting to confirm it includes: summary of findings by severity, remediation status, and trend analysis compared to prior years. 3. Assess whether the board is provided with sufficient context to understand the risk implications — not just raw finding counts. 4. Confirm that year-over-year trend analysis identifies whether the entity's security posture is improving, stable, or deteriorating based on penetration testing results. | E75: Audit committee minutes recording penetration test reporting; Penetration test summary report presented to audit committee; Year-over-year trend analysis; Board-level risk context narrative accompanying findings data | F75: Inspection | M75: =IF(K75="Compliant",3,IF(K75="Partially Compliant",2,IF(K75="Non-Compliant",1,"")))
A77: This work program is constructed for educational purposes. Customise for your engagement. Not legal or regulatory advice. AI-generated content — review and validate before use.

Sheet Cybersecurity
A1: Ref | B1: Control | C1: Sub-Procedure | D1: Assessment Procedures | E1: Expected Evidence | F1: Method | G1: Procedures Performed | H1: Evidence Obtained | I1: Evidence Ref | J1: Observation / Findings | K1: Conclusion | L1: Recommendations | M1: Score
A2: CYB-1 — Cyber Threat Management
A3: PURPOSE: SC-GL/6-2023 requires capital market intermediaries to maintain a proactive cyber threat management capability that identifies, assesses, and responds to threats targeting capital market operations. This ensures the entity operates with current threat awareness rather than relying solely on reactive defences. EXPECTATION: The assessor should find an active threat intelligence programme with feeds relevant to the capital market sector (including MyCERT and SC advisories), periodic threat assessments covering capital market-specific scenarios, documented threat hunting activity, participation in industry information-sharing initiatives, and regular threat landscape reporting to the board with actionable recommendations. KEY RISK: Without effective cyber threat management, the intermediary operates blind to evolving threats targeting trading systems, market data infrastructure, and client assets, increasing the likelihood of a successful attack that disrupts market operations or compromises client data.
A4: CYB-1 | B4: Cyber Threat Management | C4: Threat intelligence programme | D4: 1. Obtain documentation of the threat intelligence programme, including subscribed feeds (government, commercial, industry) and verify each feed is active with current subscriptions. 2. Verify that subscribed feeds include sources relevant to capital market threats (e.g., MyCERT, SC Malaysia advisories, FS-ISAC, commercial CTI providers covering APAC financial sector). 3. Review the feed ingestion process and confirm threat intelligence is parsed, triaged, and routed to SOC analysts within defined SLAs. 4. Inspect a sample of 5 threat intelligence items (per sampling methodology) received in the last 6 months and trace each from ingestion through assessment to action taken (e.g., IOC deployment, detection rule creation, patch prioritisation). | E4: Threat intelligence programme charter or procedure document; list of subscribed CTI feeds with subscription confirmations; sample threat intelligence triage records (5 items, last 6 months per sampling methodology); IOC deployment logs | F4: Inspection / Inquiry | M4: =IF(K4="Compliant",3,IF(K4="Partially Compliant",2,IF(K4="Non-Compliant",1,"")))
A5: CYB-1 | B5: Cyber Threat Management | C5: Capital market threat assessment | D5: 1. Obtain the last 2 periodic threat assessment reports (covering the last 12 months per sampling methodology) and verify they address capital market-specific threat scenarios. 2. Confirm assessments cover relevant threat categories: trading system attacks, market data manipulation, DDoS against exchange connectivity, ransomware targeting settlement infrastructure, insider trading facilitation, and state-sponsored threats to financial markets. 3. Verify threat assessments reference the entity's specific technology footprint (trading platforms, OMS/EMS, market data feeds, Bursa Malaysia connectivity). 4. Review how threat assessment findings have been translated into updated risk ratings or control priorities in the technology risk register. | E5: Periodic threat assessment reports (last 2 cycles); technology risk register with threat-driven updates; threat scenario documentation referencing capital market systems | F5: Inspection | M5: =IF(K5="Compliant",3,IF(K5="Partially Compliant",2,IF(K5="Non-Compliant",1,"")))
A6: CYB-1 | B6: Cyber Threat Management | C6: Threat hunting capability | D6: 1. Interview threat hunting personnel (or SOC analysts performing hunting duties) to understand hunting methodology, tools, and frequency. 2. Obtain threat hunting reports or logs from the last 12 months (per sampling methodology) and verify at least 3 proactive hunts were conducted (per sampling methodology). 3. Review hunting hypotheses to confirm they target advanced persistent threats relevant to capital market intermediaries (e.g., credential theft targeting trading systems, lateral movement toward settlement infrastructure, data exfiltration of client positions). 4. Determine whether hunting findings have resulted in new detection rules, IOC updates, or control improvements. 5. Verify that threat hunting covers algorithmic trading infrastructure and market data feed systems, not just generic enterprise IT. | E6: Threat hunting reports (last 12 months per sampling methodology); hunting hypothesis documentation; new detection rules created from hunting findings; threat hunting tools inventory | F6: Inspection / Inquiry | M6: =IF(K6="Compliant",3,IF(K6="Partially Compliant",2,IF(K6="Non-Compliant",1,"")))
A7: CYB-1 | B7: Cyber Threat Management | C7: Threat information sharing | D7: 1. Obtain evidence of participation in SC Malaysia threat information sharing initiatives, MyCERT coordination, and any capital market industry working groups or ISACs. 2. Review records of threat intelligence shared with and received from peer institutions, regulators, and industry bodies over the last 12 months. 3. Verify the entity has designated contacts and defined procedures for receiving and acting on SC advisories and MyCERT alerts. 4. Confirm participation records show active engagement (not merely membership) through meeting attendance, intelligence contributions, or exercise participation. | E7: SC advisory distribution and acknowledgement records; MyCERT coordination records; ISAC or working group membership and attendance records (last 12 months); evidence of intelligence contributions shared externally | F7: Inspection / Inquiry | M7: =IF(K7="Compliant",3,IF(K7="Partially Compliant",2,IF(K7="Non-Compliant",1,"")))
A8: CYB-1 | B8: Cyber Threat Management | C8: Threat landscape reporting | D8: 1. Obtain threat landscape reports or briefings provided to senior management and the board over the last 4 quarters. 2. Verify reports cover emerging threats to the capital market sector, threat actor trends (nation-state, organised crime, hacktivists), and specific risks to the entity's market operations. 3. Confirm reports include actionable recommendations and track implementation status of previously recommended actions. 4. Review whether threat landscape reporting has triggered any out-of-cycle risk assessments, budget requests, or control enhancements. | E8: Quarterly threat landscape reports or board briefing slides (last 4 quarters); board/committee meeting minutes noting threat briefing discussions; action item tracking from threat briefings | F8: Inspection | M8: =IF(K8="Compliant",3,IF(K8="Partially Compliant",2,IF(K8="Non-Compliant",1,"")))
A9: CYB-1 | B9: Cyber Threat Management | C9: Threat-driven control updates | D9: 1. Select a sample of 3 significant threat intelligence items or threat assessment findings from the last 12 months (per sampling methodology) and trace each to corresponding control updates. 2. Verify the process from threat identification to control update follows a defined workflow with documented approvals and timelines. 3. Review examples of control updates driven by threat intelligence (e.g., new firewall rules, updated detection signatures, additional access restrictions on trading systems, patching prioritisation changes). 4. Confirm that a feedback loop exists where control effectiveness is re-assessed after threat-driven changes are implemented. | E9: Change records linked to threat intelligence triggers; detection rule update logs; firewall change requests referencing threat intelligence; post-implementation verification records | F9: Inspection | M9: =IF(K9="Compliant",3,IF(K9="Partially Compliant",2,IF(K9="Non-Compliant",1,"")))
A10: CYB-2 — Security Operations Centre [CRITICAL]
A11: PURPOSE: SC-GL/6-2023 requires capital market intermediaries to maintain a security operations centre (SOC) as the primary detection and monitoring capability for cyber threats to capital market systems. The SOC is the frontline defence that detects attacks on trading platforms, settlement systems, and market data infrastructure in real time. EXPECTATION: The assessor should find a SOC with appropriate architecture and staffing for 24/7 coverage, comprehensive SIEM log source coverage including all critical capital market systems, detection rules tuned for capital market-specific attack patterns, enhanced monitoring during Bursa Malaysia trading hours, documented alert handling with defined SLAs, regular performance metrics reporting, and periodic effectiveness assessments including purple team testing. KEY RISK: A deficient SOC directly compromises the intermediary's ability to detect and respond to active cyber attacks on trading systems, exchange connectivity, and settlement infrastructure, potentially allowing threat actors extended dwell time to manipulate markets, exfiltrate client data, or disrupt capital market operations.
A12: CYB-2 | B12: Security Operations Centre | C12: SOC deployment and architecture | D12: 1. Obtain the SOC architecture documentation, including deployment model (in-house, MSSP, hybrid) and technology stack (SIEM, SOAR, EDR, NDR). 2. Review the SOC charter or terms of reference defining scope of monitoring, escalation authority, and integration with incident response. 3. Verify the SOC deployment model is appropriate for the entity's scale, with clear contractual obligations if MSSP is used (including SLAs for capital market-specific monitoring). 4. Confirm the SOC has documented runbooks for capital market-specific scenarios (trading system compromise, market data feed disruption, exchange connectivity anomalies, Bursa Malaysia link failure). | E12: SOC architecture document; SOC charter or terms of reference; MSSP contract with SLAs (if applicable); SOC runbook inventory covering capital market scenarios | F12: Inspection / Inquiry | M12: =IF(K12="Compliant",3,IF(K12="Partially Compliant",2,IF(K12="Non-Compliant",1,"")))
A13: CYB-2 | B13: Security Operations Centre | C13: SIEM log source coverage | D13: 1. Obtain the complete log source inventory feeding into the SIEM and compare against the entity's critical asset register. 2. Verify that all critical capital market systems are included: trading platforms (OMS/EMS), settlement systems, market data feed handlers, Bursa Malaysia connectivity gateways, client portals, algorithmic trading engines, and privileged access management systems. 3. Confirm log ingestion rates are within SIEM capacity and no critical log sources are being dropped or delayed. 4. Review the last log source coverage gap analysis and verify identified gaps have been remediated. 5. Inspect SIEM health dashboards to confirm all critical log sources show active and current data flow. | E13: SIEM log source inventory; critical asset register cross-reference; SIEM health/ingestion dashboard screenshots; log source coverage gap analysis report | F13: Inspection | M13: =IF(K13="Compliant",3,IF(K13="Partially Compliant",2,IF(K13="Non-Compliant",1,"")))
A14: CYB-2 | B14: Security Operations Centre | C14: Detection rules and use cases | D14: 1. Obtain the SIEM detection rule inventory and verify total rule count, categorisation, and last review date for each rule. 2. Select a sample of 15 detection rules (per sampling methodology for critical-tier controls) and assess whether they are tuned for capital market-specific attack patterns: unusual trading volumes or order patterns, market data manipulation attempts, unauthorised access to trading systems, privileged account abuse on settlement infrastructure, exchange connectivity anomalies. 3. Review the detection engineering process for creating, testing, and deploying new rules, including how false positive rates are managed. 4. Verify that detection rules are updated in response to new threat intelligence, recent incidents, and changes to the technology environment. 5. Confirm that detection rules cover MITRE ATT&CK techniques relevant to financial sector threat actors. | E14: SIEM detection rule inventory with review dates; sample detection rule configurations (15 rules per sampling methodology); detection engineering change log; false positive tuning records; MITRE ATT&CK coverage mapping | F14: Inspection / Inquiry | M14: =IF(K14="Compliant",3,IF(K14="Partially Compliant",2,IF(K14="Non-Compliant",1,"")))
A15: CYB-2 | B15: Security Operations Centre | C15: Trading hours and after-hours monitoring | D15: 1. Verify 24/7 monitoring coverage by reviewing SOC shift rosters for the last 3 months (per sampling methodology for operational records), confirming continuous staffing or MSSP coverage across all shifts. 2. Confirm that monitoring during Bursa Malaysia trading hours (pre-market, continuous trading, closing) has enhanced alerting thresholds and faster escalation SLAs. 3. Review after-hours monitoring procedures for batch settlement processing, overnight reconciliation runs, and market data feed maintenance windows. 4. Verify that weekend and public holiday monitoring covers scheduled maintenance, DR testing, and any overnight trading activity (e.g., global market exposure). 5. Interview SOC shift leads to confirm awareness of trading calendar, settlement deadlines, and market-critical time windows. | E15: SOC shift rosters (last 3 months per sampling methodology); trading hours escalation SLA documentation; after-hours monitoring procedures; Bursa Malaysia trading calendar integration evidence; weekend/holiday coverage records | F15: Inspection / Inquiry | M15: =IF(K15="Compliant",3,IF(K15="Partially Compliant",2,IF(K15="Non-Compliant",1,"")))
A16: CYB-2 | B16: Security Operations Centre | C16: Alert handling and triage | D16: 1. Select a sample of 8 security alerts from the last 3 months (per sampling methodology for critical-tier controls) and trace each from initial detection through triage, investigation, and disposition. 2. Verify each alert was triaged within the defined SLA and assigned an appropriate severity based on documented criteria. 3. Confirm that alert disposition is documented (true positive escalated, false positive with tuning action, benign true positive acknowledged). 4. Review alert escalation procedures and verify at least 3 escalated alerts reached the appropriate response team with documented handoff. 5. Determine whether trading system-related alerts receive priority handling compared to general IT alerts. | E16: Sample alert tickets with full lifecycle (8 alerts per sampling methodology); alert triage SLA compliance report; escalation records with handoff documentation (minimum 3); alert severity classification criteria | F16: Inspection | M16: =IF(K16="Compliant",3,IF(K16="Partially Compliant",2,IF(K16="Non-Compliant",1,"")))
A17: CYB-2 | B17: Security Operations Centre | C17: SOC performance metrics | D17: 1. Obtain SOC performance reports for the last 4 quarters and verify they track key metrics: mean time to detect (MTTD), mean time to respond (MTTR), alert volume trends, false positive rates, and escalation counts. 2. Verify MTTD and MTTR meet defined targets, particularly for critical-severity alerts affecting trading or settlement systems. 3. Review alert volume trends to identify whether volumes are increasing, stable, or decreasing and whether the SOC has adequate capacity. 4. Confirm metrics are reported to CISO and senior management with analysis of trends and recommended improvements. 5. Compare current quarter metrics against previous quarters to assess whether SOC performance is improving or degrading. | E17: Quarterly SOC performance reports (last 4 quarters); MTTD/MTTR trend data; alert volume analysis; SOC capacity assessment; management reporting on SOC metrics | F17: Inspection | M17: =IF(K17="Compliant",3,IF(K17="Partially Compliant",2,IF(K17="Non-Compliant",1,"")))
A18: CYB-2 | B18: Security Operations Centre | C18: SOC effectiveness assessment | D18: 1. Obtain the most recent SOC effectiveness assessment or maturity review (internal or external) conducted within the last 24 months. 2. Review the assessment scope and verify it covered people, process, and technology dimensions of SOC operations. 3. Inspect findings and recommendations, and verify an action plan was developed with assigned owners and target dates. 4. Confirm progress against the action plan by reviewing status updates and verify critical recommendations have been addressed. 5. Determine whether the assessment included testing of detection capability through purple team exercises or simulated attack scenarios targeting capital market systems. | E18: SOC effectiveness assessment report (most recent); remediation action plan with status tracking; purple team or detection testing results; SOC maturity scorecard | F18: Inspection | M18: =IF(K18="Compliant",3,IF(K18="Partially Compliant",2,IF(K18="Non-Compliant",1,"")))
A19: CYB-2 | B19: Security Operations Centre | C19: SOC staffing and skills | D19: 1. Review the SOC organisational structure, headcount, and verify staffing levels are adequate for 24/7 coverage without excessive overtime or single points of failure. 2. Obtain SOC analyst training records for the last 12 months and verify analysts have received training on capital market systems, trading protocols, and relevant regulatory requirements. 3. Confirm SOC analysts hold relevant certifications (e.g., GCIA, GCIH, OSCP, vendor-specific SIEM certifications) and the team has a skills development plan. 4. Interview SOC management on staff retention, succession planning, and how knowledge of capital market-specific threats and systems is maintained across the team. 5. Verify that onboarding procedures for new SOC analysts include orientation on capital market operations, critical system topology, and trading hour requirements. | E19: SOC organisational chart with headcount; analyst training records (last 12 months); certification inventory; skills development plan; staff retention and succession documentation; analyst onboarding checklist | F19: Inspection / Inquiry | M19: =IF(K19="Compliant",3,IF(K19="Partially Compliant",2,IF(K19="Non-Compliant",1,"")))
A20: CYB-3 — Vulnerability Management Programme
A21: PURPOSE: SC-GL/6-2023 requires capital market intermediaries to operate a comprehensive vulnerability management programme that systematically identifies, prioritises, and remediates vulnerabilities across all capital market systems. This ensures known weaknesses are addressed before they can be exploited by threat actors. EXPECTATION: The assessor should find a documented vulnerability management programme with defined scanning frequency and scope covering all capital market systems, risk-based patching SLAs that account for trading operational constraints, patch compliance tracking with management reporting, integration with penetration testing findings, a governed exception process, and quarterly trend reporting to the CISO and board. KEY RISK: Unpatched vulnerabilities in trading platforms, settlement systems, and exchange connectivity create exploitable attack vectors that could be leveraged for market disruption, data breach, or unauthorized access to client trading positions.
A22: CYB-3 | B22: Vulnerability Management Programme | C22: Vulnerability scanning programme | D22: 1. Obtain the vulnerability management policy or procedure and verify it defines scanning frequency, tools, responsibilities, and scope. 2. Review the scanning schedule and confirm scans are executed at the required frequency (e.g., weekly or monthly for critical systems, quarterly for others). 3. Verify that scanning tools are current, licensed, and configured with up-to-date vulnerability signatures. 4. Inspect the last 3 scan execution reports (per sampling methodology for operational records) to confirm scans completed successfully without premature termination or configuration errors. 5. Confirm that authenticated scanning is used for critical capital market systems to ensure accurate detection depth. | E22: Vulnerability management policy/procedure; scanning schedule; scanning tool licence and configuration records; scan execution reports (last 3 scans per sampling methodology); authenticated scan configuration evidence | F22: Inspection | M22: =IF(K22="Compliant",3,IF(K22="Partially Compliant",2,IF(K22="Non-Compliant",1,"")))
A23: CYB-3 | B23: Vulnerability Management Programme | C23: Asset coverage and scope | D23: 1. Obtain the vulnerability scanning asset scope and compare against the entity's complete IT asset register and critical system inventory. 2. Verify that all capital market systems are included in scanning scope: trading platforms, OMS/EMS, settlement systems, market data feed infrastructure, client portals, algorithmic trading engines, and supporting middleware. 3. Identify any systems excluded from scanning (e.g., legacy trading systems, vendor-managed platforms) and verify documented risk acceptance with compensating controls. 4. Confirm that cloud-hosted capital market workloads are included in the scanning programme. 5. Review asset discovery procedures to ensure new systems are added to scanning scope within a defined timeframe after deployment. | E23: Vulnerability scanning scope document; IT asset register cross-reference; excluded assets register with risk acceptance approvals; cloud workload scanning evidence; asset discovery procedure | F23: Inspection | M23: =IF(K23="Compliant",3,IF(K23="Partially Compliant",2,IF(K23="Non-Compliant",1,"")))
A24: CYB-3 | B24: Vulnerability Management Programme | C24: Risk-based patching SLAs | D24: 1. Obtain the patch management policy and verify defined SLAs by vulnerability severity: critical (e.g., 72 hours), high (e.g., 14 days), medium (e.g., 30 days), low (e.g., 90 days). 2. Verify that SLAs account for capital market operational constraints, including trading windows, settlement cycles, and market closure periods for applying patches. 3. Review the emergency patching procedure for zero-day vulnerabilities affecting production trading systems, including approval workflow, testing requirements, and rollback plans. 4. Confirm that SLAs differentiate between internet-facing systems, internal capital market systems, and supporting infrastructure. 5. Interview the patch management team to understand how patching of trading systems is coordinated with market operations to minimise disruption during trading hours. | E24: Patch management policy with SLAs; emergency patching procedure; trading system patch coordination records; SLA definitions by system classification | F24: Inspection / Inquiry | M24: =IF(K24="Compliant",3,IF(K24="Partially Compliant",2,IF(K24="Non-Compliant",1,"")))
A25: CYB-3 | B25: Vulnerability Management Programme | C25: Patch compliance and SLA adherence | D25: 1. Obtain patch compliance reports for the last 3 months (per sampling methodology for operational records) and verify overall compliance rates against defined SLAs. 2. Select a sample of 10 critical and high vulnerabilities identified in the last 6 months (per sampling methodology) and trace each from identification through patching to closure, verifying SLA compliance. 3. Review the current count of overdue patches by severity and system classification, with particular attention to overdue patches on trading and settlement systems. 4. Verify that patch compliance metrics are reported to CISO and senior management with trend analysis. 5. Confirm that patch deployment to capital market systems follows a defined testing and change management process before production rollout. | E25: Patch compliance reports (last 3 months per sampling methodology); sample vulnerability-to-patch trace records (10 items per sampling methodology); overdue patch inventory; management patch compliance dashboards; change records for patches applied to trading systems | F25: Inspection | M25: =IF(K25="Compliant",3,IF(K25="Partially Compliant",2,IF(K25="Non-Compliant",1,"")))
A26: CYB-3 | B26: Vulnerability Management Programme | C26: Penetration testing integration | D26: 1. Obtain the most recent penetration testing report (within last 12 months per sampling methodology for annual processes) and verify it was conducted by qualified independent testers. 2. Confirm the penetration test scope included critical capital market systems: trading platforms, settlement systems, client-facing portals, market data infrastructure, and external connectivity points. 3. Verify that penetration testing findings have been fed into the vulnerability management programme with appropriate severity ratings and remediation SLAs. 4. Review remediation status of penetration testing findings, selecting a sample of 5 critical/high findings (per sampling methodology) to confirm timely closure. 5. Determine whether penetration testing includes testing of Bursa Malaysia connectivity security, algorithmic trading API endpoints, and FIX protocol implementations. | E26: Penetration testing report (most recent, last 12 months); tester qualification evidence; scope documentation; finding remediation tracking; sample finding closure evidence (5 findings per sampling methodology) | F26: Inspection | M26: =IF(K26="Compliant",3,IF(K26="Partially Compliant",2,IF(K26="Non-Compliant",1,"")))
A27: CYB-3 | B27: Vulnerability Management Programme | C27: Exception and risk acceptance management | D27: 1. Obtain the vulnerability exception or risk acceptance register and review all current open exceptions. 2. Verify each exception has documented business justification, risk owner approval at appropriate authority level, defined compensating controls, and a review/expiry date. 3. Select a sample of 5 exceptions (per sampling methodology) and verify compensating controls are in place and effective. 4. Review expired exceptions to confirm they were re-assessed and either remediated or formally renewed. 5. Confirm that exceptions for vulnerabilities on trading and settlement systems require CISO or senior management approval. | E27: Vulnerability exception/risk acceptance register; exception approval records with risk owner sign-off; compensating control documentation (5 exceptions per sampling methodology); exception review/renewal records; approval authority matrix for exceptions | F27: Inspection | M27: =IF(K27="Compliant",3,IF(K27="Partially Compliant",2,IF(K27="Non-Compliant",1,"")))
A28: CYB-3 | B28: Vulnerability Management Programme | C28: Vulnerability trending and reporting | D28: 1. Obtain vulnerability trend reports for the last 4 quarters and verify they track total vulnerability counts, new vulnerabilities identified, remediated, and remaining open by severity. 2. Review whether trending data shows improvement or deterioration in the entity's vulnerability posture, particularly for capital market systems. 3. Verify that recurring vulnerability categories (e.g., same vulnerability class appearing across multiple scan cycles) are identified and root cause analysis is conducted. 4. Confirm vulnerability trending reports are provided to CISO and board/risk committee with recommendations for systemic improvements. 5. Determine whether vulnerability data is correlated with threat intelligence to prioritise remediation based on active exploitation in the capital market sector. | E28: Quarterly vulnerability trend reports (last 4 quarters); root cause analysis for recurring vulnerabilities; management reporting with trend analysis; threat-informed prioritisation evidence | F28: Inspection | M28: =IF(K28="Compliant",3,IF(K28="Partially Compliant",2,IF(K28="Non-Compliant",1,"")))
A29: CYB-4 — Network Security Architecture
A30: PURPOSE: SC-GL/6-2023 requires capital market intermediaries to maintain a secure network architecture with appropriate segmentation between trading, settlement, corporate, and market data environments. This ensures that network design supports defence in depth and limits the blast radius of any security compromise. EXPECTATION: The assessor should find a documented and current network architecture with distinct segments for trading, settlement, market data, corporate, and DMZ environments. Firewall rules should enforce least-privilege inter-segment access, IDS/IPS sensors should cover all critical segments, exchange connectivity should use dedicated secure channels, and the architecture should be reviewed at least annually against the current threat landscape. KEY RISK: Poor network segmentation allows lateral movement from compromised corporate systems into trading and settlement networks, enabling attackers to disrupt market operations, manipulate trading activity, or intercept market data feeds.
A31: CYB-4 | B31: Network Security Architecture | C31: Network architecture documentation | D31: 1. Obtain the current network architecture diagram and verify it is dated, version-controlled, and approved by the network security team or CTO. 2. Verify the diagram accurately reflects the production environment, including all network zones, VLAN assignments, and connectivity paths for capital market systems. 3. Confirm the diagram identifies all external connectivity points: Bursa Malaysia links, clearing house connections, market data provider feeds, client VPN/API gateways, and internet-facing services. 4. Review the diagram update process and confirm it is updated within a defined timeframe after network changes. 5. Interview the network team to confirm the diagram reflects the as-built environment, not just the designed state. | E31: Network architecture diagram (current version, dated); diagram version history; network change log cross-referenced to diagram updates; external connectivity inventory | F31: Inspection / Inquiry | M31: =IF(K31="Compliant",3,IF(K31="Partially Compliant",2,IF(K31="Non-Compliant",1,"")))
A32: CYB-4 | B32: Network Security Architecture | C32: Network segmentation — trading, settlement, corporate, and market data | D32: 1. Verify that distinct network segments exist for: (a) trading systems and OMS/EMS, (b) settlement and clearing systems, (c) market data feed infrastructure, (d) corporate/office network, (e) client-facing DMZ, and (f) management/administrative network. 2. Review VLAN configurations and routing tables to confirm segments are logically or physically separated with controlled inter-segment access. 3. Inspect firewall or access control policies governing traffic between trading networks and corporate networks, confirming least-privilege rules with no overly permissive paths. 4. Verify that algorithmic trading infrastructure is segmented with dedicated network paths to exchange connectivity, isolated from general corporate traffic. 5. Test a sample of 3 inter-segment access rules (per sampling methodology) by reviewing recent traffic logs to confirm only authorised traffic flows between zones. | E32: VLAN configuration documentation; inter-segment firewall rule sets; routing table extracts; network traffic flow analysis for inter-segment paths (3 rules per sampling methodology); algorithmic trading network isolation evidence | F32: Inspection / Observation | M32: =IF(K32="Compliant",3,IF(K32="Partially Compliant",2,IF(K32="Non-Compliant",1,"")))
A33: CYB-4 | B33: Network Security Architecture | C33: IDS/IPS deployment and monitoring | D33: 1. Obtain the IDS/IPS deployment inventory and verify sensors are deployed on all critical network segments: trading network perimeter, settlement system segments, market data feed paths, internet-facing DMZ, and Bursa Malaysia connectivity. 2. Review IDS/IPS signature update procedures and confirm signatures are updated at least weekly, with emergency updates for critical threats. 3. Select a sample of 5 IDS/IPS alerts from the last 3 months (per sampling methodology) and verify each was triaged, investigated, and dispositioned according to documented procedures. 4. Confirm IDS/IPS operates in prevention mode (IPS) for internet-facing segments and verify the policy for detection-only vs. prevention mode on internal trading network segments. 5. Review IDS/IPS performance metrics including alert volumes, false positive rates, and any detection blind spots identified in the last review. | E33: IDS/IPS deployment map with sensor locations; signature update logs; sample alert investigation records (5 alerts per sampling methodology); IPS mode configuration evidence; IDS/IPS performance metrics report | F33: Inspection | M33: =IF(K33="Compliant",3,IF(K33="Partially Compliant",2,IF(K33="Non-Compliant",1,"")))
A34: CYB-4 | B34: Network Security Architecture | C34: Market data feed and exchange connectivity security | D34: 1. Obtain documentation of all market data feed connections and exchange connectivity (Bursa Malaysia, Bursa Malaysia Derivatives, clearing houses, central depository) and verify security controls for each. 2. Verify that exchange connectivity uses dedicated leased lines, encrypted VPN tunnels, or SC-approved secure channels with mutual authentication. 3. Review access controls on market data feed handlers and confirm only authorised trading systems and personnel can access raw market data. 4. Inspect FIX protocol gateway configurations for authentication, session management, message validation, and heartbeat monitoring. 5. Confirm that market data feed redundancy and failover paths are secured with equivalent controls to primary paths. | E34: Exchange connectivity inventory with security controls; leased line or VPN configuration records; market data feed access control lists; FIX gateway configuration extracts; failover path security documentation | F34: Inspection / Inquiry | M34: =IF(K34="Compliant",3,IF(K34="Partially Compliant",2,IF(K34="Non-Compliant",1,"")))
A35: CYB-4 | B35: Network Security Architecture | C35: Firewall rule management | D35: 1. Obtain the firewall rule management policy and verify it defines rule request, approval, implementation, and periodic review processes. 2. Review the last firewall rule review (conducted within last 12 months per sampling methodology for annual processes) and verify unused, redundant, or overly permissive rules were identified and remediated. 3. Select a sample of 5 firewall rule change requests from the last 6 months (per sampling methodology) and verify each followed the defined approval workflow with business justification and security review. 4. Inspect firewall rule sets for any-to-any rules, rules permitting direct internet access from trading networks, or rules with no expiry date on temporary access. 5. Verify that firewall rules governing Bursa Malaysia connectivity and clearing house connections are reviewed by both network security and market operations teams. | E35: Firewall rule management policy; last firewall rule review report (last 12 months); sample firewall change requests with approvals (5 changes per sampling methodology); firewall rule set extracts for critical segments; Bursa connectivity rule review records | F35: Inspection | M35: =IF(K35="Compliant",3,IF(K35="Partially Compliant",2,IF(K35="Non-Compliant",1,"")))
A36: CYB-4 | B36: Network Security Architecture | C36: Network architecture review | D36: 1. Obtain the most recent network architecture review report (conducted within last 12 months) and verify it assessed the architecture against the current threat landscape and SC-GL/6-2023 requirements. 2. Verify the review scope covered all capital market network segments including trading, settlement, market data, and external connectivity. 3. Review findings and recommendations, and confirm an action plan was developed with assigned owners, target dates, and progress tracking. 4. Determine whether the review assessed the architecture's resilience to common attack scenarios: lateral movement from corporate to trading networks, DDoS against exchange connectivity, man-in-the-middle on market data feeds. 5. Confirm that the network architecture review considered emerging requirements such as zero-trust principles, microsegmentation, and software-defined networking for capital market infrastructure. | E36: Network architecture review report (most recent); review scope documentation; findings remediation action plan with status; threat scenario assessment evidence; zero-trust readiness assessment | F36: Inspection | M36: =IF(K36="Compliant",3,IF(K36="Partially Compliant",2,IF(K36="Non-Compliant",1,"")))
A38: This work program is constructed for educational purposes. Customise for your engagement. Not legal or regulatory advice. AI-generated content — review and validate before use.

Sheet Resilience & Incident Managemen
A1: Ref | B1: Control | C1: Sub-Procedure | D1: Assessment Procedures | E1: Expected Evidence | F1: Method | G1: Procedures Performed | H1: Evidence Obtained | I1: Evidence Ref | J1: Observation / Findings | K1: Conclusion | L1: Recommendations | M1: Score
A2: RIM-1 — BCM Programme for Market Operations [CRITICAL]
A3: PURPOSE: SC-GL/6-2023 requires capital market intermediaries to maintain a comprehensive business continuity management programme because disruption to trading, clearing, or settlement operations can cascade across the entire market ecosystem. The BCM programme ensures the intermediary can sustain or rapidly restore critical market functions, protecting investors and preserving market integrity. EXPECTATION: The assessor should find a board-approved BCM programme with a current BIA that quantifies maximum tolerable downtime for each capital market function, BCPs with market-specific recovery strategies, and validated RTO/RPO targets. Coordination arrangements with Bursa Malaysia and clearing houses should be documented and tested. KEY RISK: Absence of an effective BCM programme exposes the intermediary to prolonged trading halts, settlement failures, and inability to manage client positions during disruptions — resulting in direct financial loss, regulatory sanctions, and erosion of market confidence.
A4: RIM-1 | B4: BCM Programme for Market Operations | C4: BIA for capital market functions | D4: 1. Obtain the business impact analysis (BIA) for capital market functions. 2. Verify the BIA covers trading, clearing, settlement, custody, and client services with assigned criticality levels. 3. Confirm that impact timelines (maximum tolerable downtime) are quantified for each function in terms of financial loss, regulatory breach, and market disruption. 4. Determine whether the BIA was reviewed and updated within the last 12 months (per sampling methodology) or after a material change in operations. | E4: BIA document for capital market operations; criticality classification matrix; BIA review/approval records (last 12 months) | F4: Inspection | M4: =IF(K4="Compliant",3,IF(K4="Partially Compliant",2,IF(K4="Non-Compliant",1,"")))
A5: RIM-1 | B5: BCM Programme for Market Operations | C5: BCP coverage for trading, clearing, and settlement | D5: 1. Obtain the BCP document and verify it addresses recovery strategies for trading, clearing, settlement, and custody operations. 2. Review whether the BCP defines activation triggers, escalation paths, and roles for each capital market function. 3. Confirm that the BCP addresses scenarios specific to market operations — trading halt, clearing system failure, settlement cycle disruption during T+2 window. 4. Verify that the BCP has been approved by senior management or the board within the last 12 months (per sampling methodology). | E5: BCP document covering trading, clearing, settlement, and custody; BCP approval records; scenario coverage matrix | F5: Inspection | M5: =IF(K5="Compliant",3,IF(K5="Partially Compliant",2,IF(K5="Non-Compliant",1,"")))
A6: RIM-1 | B6: BCM Programme for Market Operations | C6: RTO and RPO definitions and validation | D6: 1. Review defined RTO and RPO targets for each critical capital market system (order management, trade matching, clearing engine, settlement processing). 2. Verify that RTOs account for market trading hours and settlement cycle deadlines (T+2). 3. Confirm that RTO/RPO targets have been validated through actual DR testing within the last 12 months (per sampling methodology). 4. Determine whether any validation tests failed to meet targets, and review remediation actions taken. | E6: RTO/RPO register for critical market systems; DR test results validating RTO/RPO achievement; remediation records for any missed targets | F6: Inspection | M6: =IF(K6="Compliant",3,IF(K6="Partially Compliant",2,IF(K6="Non-Compliant",1,"")))
A7: RIM-1 | B7: BCM Programme for Market Operations | C7: Coordination with market operators and clearing houses | D7: 1. Obtain records of coordination with Bursa Malaysia, clearing houses, and central depository for business continuity planning. 2. Verify that agreed communication protocols exist for notifying market operators during a disruption event. 3. Review whether the entity participates in joint BCP planning or tabletop exercises with market infrastructure providers. 4. Interview the BCM Manager to assess the maturity of coordination relationships and any gaps identified. | E7: Coordination records with Bursa Malaysia and clearing houses; agreed communication protocols; joint exercise participation records | F7: Inspection / Inquiry | M7: =IF(K7="Compliant",3,IF(K7="Partially Compliant",2,IF(K7="Non-Compliant",1,"")))
A8: RIM-1 | B8: BCM Programme for Market Operations | C8: BCP review cycle and continuous improvement | D8: 1. Obtain the BCP review schedule and verify the plan has been reviewed at least annually (per sampling methodology) or after significant incidents, organisational changes, or DR test findings. 2. Review the change log for the BCP document to confirm updates reflect lessons learned from tests, incidents, and regulatory changes. 3. Interview the BCM Manager or COO to understand how lessons from actual disruptions and DR exercises are incorporated into the BCP. 4. Verify that BCP review outcomes are reported to senior management or the board. | E8: BCP review schedule and change log; board or management reporting on BCP reviews; evidence of updates post-incident or post-exercise | F8: Inspection / Inquiry | M8: =IF(K8="Compliant",3,IF(K8="Partially Compliant",2,IF(K8="Non-Compliant",1,"")))
A9: RIM-2 — Trading System Resilience [CRITICAL]
A10: PURPOSE: SC-GL/6-2023 requires resilient trading infrastructure because intermediary system failures can disrupt market access for investors and impair orderly price discovery. Trading system resilience ensures continuous order execution capability and prevents intermediary-level outages from cascading into broader market disruption. EXPECTATION: The assessor should find documented redundant trading architecture with active failover capability, capacity planning for high-volatility scenarios, tested alternative trading channels, and real-time monitoring with automated alerting. Failover tests should demonstrate achievement of RTO targets under realistic mid-session failure conditions. KEY RISK: Trading system failure during market hours results in inability to execute client orders, manage open positions, or meet margin obligations — exposing the intermediary to client losses, regulatory penalties, and potential forced position liquidation by the exchange.
A11: RIM-2 | B11: Trading System Resilience | C11: Redundant trading infrastructure | D11: 1. Obtain the trading system architecture documentation, including network diagrams and infrastructure design. 2. Verify that the architecture employs redundancy at each critical layer — servers, databases, network paths, and trading venue connectivity. 3. Confirm whether the design is active-active or active-passive, and determine the rationale for the chosen configuration. 4. Review whether order management systems (OMS) and market data feeds have redundant pathways to Bursa Malaysia. | E11: Trading system architecture diagrams; infrastructure design documentation; redundancy configuration details for OMS, market data, and venue connectivity | F11: Inspection | M11: =IF(K11="Compliant",3,IF(K11="Partially Compliant",2,IF(K11="Non-Compliant",1,"")))
A12: RIM-2 | B12: Trading System Resilience | C12: Failover capability and testing | D12: 1. Obtain failover test reports from the last 12 months (per sampling methodology) for primary trading systems. 2. Review test objectives, measured failover times, and whether failover completed within defined RTO targets. 3. Verify that failover testing included realistic scenarios — mid-session failure during market hours, database replication switchover, and market data feed failover. 4. Confirm that issues identified during failover tests have been remediated and retested. | E12: Failover test reports (last 12 months); test results against RTO targets; issue remediation records from failover tests | F12: Inspection | M12: =IF(K12="Compliant",3,IF(K12="Partially Compliant",2,IF(K12="Non-Compliant",1,"")))
A13: RIM-2 | B13: Trading System Resilience | C13: Capacity planning for market volatility | D13: 1. Obtain capacity planning documentation for trading systems. 2. Verify that capacity thresholds are defined with headroom for high-volatility scenarios (e.g., 2x-3x normal trading volume). 3. Review monitoring data or capacity reports from the last 12 months (per sampling methodology) to confirm peak utilisation levels and remaining headroom. 4. Determine whether capacity planning accounts for Bursa Malaysia market structure changes, new product launches, or anticipated volume increases. | E13: Capacity planning documentation; capacity utilisation reports (last 12 months); headroom calculations for peak trading scenarios | F13: Inspection | M13: =IF(K13="Compliant",3,IF(K13="Partially Compliant",2,IF(K13="Non-Compliant",1,"")))
A14: RIM-2 | B14: Trading System Resilience | C14: Alternative trading channels | D14: 1. Obtain documentation of alternative trading channels or manual order submission procedures available when primary systems are unavailable. 2. Verify that alternative channels allow the entity to manage open positions, submit essential orders, and communicate with Bursa Malaysia during primary system outages. 3. Review whether alternative channel procedures have been tested within the last 12 months (per sampling methodology), including test results. 4. Interview the Head of Trading Technology to confirm staff are trained on alternative channel procedures. | E14: Alternative trading channel procedures; test records for alternative channels (last 12 months); staff training records | F14: Inspection / Inquiry | M14: =IF(K14="Compliant",3,IF(K14="Partially Compliant",2,IF(K14="Non-Compliant",1,"")))
A15: RIM-2 | B15: Trading System Resilience | C15: Real-time monitoring and automated alerting | D15: 1. Review real-time health monitoring configuration for trading systems, including monitored parameters (latency, throughput, error rates, connectivity status). 2. Verify that automated alerts are configured to trigger when trading system health degrades beyond defined thresholds. 3. Confirm that alerting covers market data feed latency and trading venue connectivity status. 4. Obtain alert records from the last 30 days (per sampling methodology for continuous monitoring) and verify appropriate response and escalation occurred. Select 15 alert events (per sampling methodology — high risk, population 100+) and trace each from trigger through to resolution. | E15: Monitoring dashboard configuration; alert threshold definitions; alert records and response logs (last 30 days); resolution records for sampled alerts | F15: Inspection | M15: =IF(K15="Compliant",3,IF(K15="Partially Compliant",2,IF(K15="Non-Compliant",1,"")))
A16: RIM-3 — DR Testing Programme
A17: PURPOSE: SC-GL/6-2023 requires regular DR testing to validate that recovery capabilities actually work under realistic conditions, not just on paper. DR testing provides assurance that capital market systems can be recovered within stated RTO/RPO targets and that recovery procedures remain current. EXPECTATION: The assessor should find a structured annual DR test programme covering all critical capital market systems, with defined success criteria, realistic failure scenarios (including data corruption and multi-system failure), and documented results. Industry DR exercise participation with Bursa Malaysia or SC Malaysia should be evidenced. KEY RISK: Untested DR plans create false confidence — the intermediary may discover recovery gaps only during an actual disruption, when it is too late to prevent extended outages affecting trading, settlement, and regulatory obligations.
A18: RIM-3 | B18: DR Testing Programme | C18: DR test programme and schedule | D18: 1. Obtain the current-year DR test plan and verify it covers all critical capital market systems (trading, clearing, settlement, market data). 2. Review test objectives and scenarios to confirm they include realistic failure conditions — not just basic switchover but also data corruption, simultaneous multi-system failure, and prolonged outage scenarios. 3. Verify that success criteria are defined for each test, including RTO/RPO achievement and data integrity verification. 4. Confirm that the DR test schedule accounts for market calendar constraints (avoiding testing during peak trading periods without appropriate controls). | E18: Current-year DR test plan; test scenario descriptions with success criteria; DR test schedule | F18: Inspection | M18: =IF(K18="Compliant",3,IF(K18="Partially Compliant",2,IF(K18="Non-Compliant",1,"")))
A19: RIM-3 | B19: DR Testing Programme | C19: Industry DR exercise participation | D19: 1. Obtain records of participation in industry-wide DR exercises coordinated by SC Malaysia or Bursa Malaysia within the last 12 months (per sampling methodology for annual processes). 2. Review the entity's role and scope of participation in the exercise. 3. Verify that findings from the industry exercise were documented and any gaps identified were addressed. 4. Interview the BCM Manager to understand how the entity prepares for industry exercises and incorporates findings. | E19: Industry DR exercise participation records (last 12 months); exercise findings and the entity's follow-up actions; correspondence with SC or Bursa regarding exercises | F19: Inspection / Inquiry | M19: =IF(K19="Compliant",3,IF(K19="Partially Compliant",2,IF(K19="Non-Compliant",1,"")))
A20: RIM-3 | B20: DR Testing Programme | C20: Data recovery and integrity testing | D20: 1. Obtain DR test reports from the last 12 months (per sampling methodology for annual processes) and identify the data recovery component of each test. 2. Verify that data recovery tests include integrity validation — reconciliation of restored data against source records, verification of transaction completeness, and confirmation of no data loss beyond defined RPO. 3. Review whether backup restoration was tested for critical databases including trade records, settlement instructions, and client account data. 4. Confirm that data recovery times achieved are within the defined RPO for each system. | E20: DR test reports with data recovery results (last 12 months); data integrity reconciliation reports; RPO achievement records | F20: Inspection | M20: =IF(K20="Compliant",3,IF(K20="Partially Compliant",2,IF(K20="Non-Compliant",1,"")))
A21: RIM-3 | B21: DR Testing Programme | C21: DR test gap remediation | D21: 1. Obtain the DR test gap remediation tracker. 2. Verify that all issues identified in DR tests from the last 12 months (per sampling methodology for annual processes) are logged with assigned owners, severity ratings, and target remediation dates. 3. Select 5 remediation items (per sampling methodology — standard risk, population 6-15) and review closure evidence to confirm gaps were actually resolved. 4. Determine whether any critical or high-severity DR gaps remain open beyond their target dates and review escalation actions. | E21: DR gap remediation tracker; closure evidence for sampled items; escalation records for overdue items | F21: Inspection | M21: =IF(K21="Compliant",3,IF(K21="Partially Compliant",2,IF(K21="Non-Compliant",1,"")))
A22: RIM-4 — Settlement Continuity
A23: PURPOSE: SC-GL/6-2023 requires settlement continuity arrangements because failure to settle within the T+2 cycle can trigger counterparty defaults, fails charges, and systemic risk across the capital market. Alternative settlement procedures ensure the intermediary can fulfill settlement obligations even during technology failures. EXPECTATION: The assessor should find documented alternative settlement procedures with defined manual processing capacity, tested fallback mechanisms, current coordination arrangements with Bursa Malaysia Depository, and post-recovery reconciliation procedures. Manual fallback should have been tested with realistic settlement volumes. KEY RISK: Settlement failure cascades into counterparty defaults and market-wide settlement disruption, resulting in fails penalties, client financial losses, and potential regulatory intervention including suspension of market participation.
A24: RIM-4 | B24: Settlement Continuity | C24: Alternative settlement procedures | D24: 1. Obtain documented alternative settlement procedures for use during technology system failures. 2. Verify the procedures cover manual processing of settlement instructions, reconciliation steps, and re-entry into automated systems after recovery. 3. Review whether the procedures define the maximum settlement volume that can be processed manually within a T+2 settlement cycle. 4. Confirm the alternative procedures were reviewed and updated within the last 12 months (per sampling methodology for annual processes). | E24: Alternative settlement procedures document; manual capacity assessment; procedure review/approval records (last 12 months) | F24: Inspection | M24: =IF(K24="Compliant",3,IF(K24="Partially Compliant",2,IF(K24="Non-Compliant",1,"")))
A25: RIM-4 | B25: Settlement Continuity | C25: BMD and Bursa Malaysia coordination | D25: 1. Obtain evidence of coordination arrangements with Bursa Malaysia Depository (BMD) for settlement continuity during disruptions. 2. Verify that agreed communication channels and escalation contacts are documented and current. 3. Review whether the entity has participated in settlement continuity planning or exercises with BMD within the last 12 months (per sampling methodology for annual processes). 4. Confirm that the entity understands BMD's own contingency procedures and how they interlock with the entity's alternative settlement process. | E25: BMD coordination arrangements; contact lists and communication channel documentation; BMD joint exercise records (last 12 months) | F25: Inspection | M25: =IF(K25="Compliant",3,IF(K25="Partially Compliant",2,IF(K25="Non-Compliant",1,"")))
A26: RIM-4 | B26: Settlement Continuity | C26: Manual fallback testing | D26: 1. Obtain test records for manual settlement fallback procedures from the last 12 months (per sampling methodology for annual processes). 2. Review the test scope — verify it included actual processing of sample settlement instructions through the manual fallback procedure. 3. Verify test results document processing times, error rates, and any issues encountered. 4. Interview the Head of Operations or Settlement Manager to confirm staff competency in executing manual fallback and understand practical constraints. | E26: Manual fallback test records (last 12 months); test results with processing times and error rates; staff competency assessments | F26: Inspection / Inquiry | M26: =IF(K26="Compliant",3,IF(K26="Partially Compliant",2,IF(K26="Non-Compliant",1,"")))
A27: RIM-4 | B27: Settlement Continuity | C27: Communication protocols with clearing and depository participants | D27: 1. Obtain documented communication protocols for notifying clearing and depository participants during settlement disruptions. 2. Verify the protocols define who communicates, to whom, through which channels, and within what timeframes. 3. Review whether communication protocols include templates or pre-drafted messages for common disruption scenarios. 4. Confirm that contact lists for clearing and depository participants are maintained and reviewed at least quarterly (per sampling methodology — last 4 quarters for board/committee records). | E27: Communication protocol documents; contact lists for clearing and depository participants; pre-drafted communication templates; contact list review records | F27: Inspection | M27: =IF(K27="Compliant",3,IF(K27="Partially Compliant",2,IF(K27="Non-Compliant",1,"")))
A28: RIM-4 | B28: Settlement Continuity | C28: Post-recovery reconciliation | D28: 1. Review documented procedures for reconciling settlement records after reverting from manual fallback to automated processing. 2. Verify reconciliation procedures address identification of discrepancies, resolution workflow, and sign-off requirements. 3. Obtain records of any actual or simulated reconciliation exercises performed after manual fallback testing. 4. Confirm that reconciliation procedures account for the T+2 settlement cycle and any penalties or fails resulting from delayed settlement. | E28: Post-recovery reconciliation procedures; reconciliation exercise records; settlement fail tracking records | F28: Inspection | M28: =IF(K28="Compliant",3,IF(K28="Partially Compliant",2,IF(K28="Non-Compliant",1,"")))
A29: RIM-5 — Incident Response Plan [CRITICAL]
A30: PURPOSE: SC-GL/6-2023 requires a structured incident response plan because capital market intermediaries face technology incidents that can disrupt trading, compromise client data, or impair market operations. A well-defined IRP ensures rapid, coordinated response that minimises market impact and meets regulatory notification obligations. EXPECTATION: The assessor should find a board-approved IRP covering all incident phases (preparation through lessons learned), a severity classification scheme calibrated to capital market impact, defined escalation procedures with market-hours awareness, a cross-functional IR team with current training, and evidence of regular tabletop exercises using capital market scenarios. KEY RISK: Without an effective IRP, incident response is ad hoc and slow — leading to extended trading disruptions, delayed regulatory notification to the SC, uncontained data breaches, and amplified financial and reputational damage.
A31: RIM-5 | B31: Incident Response Plan | C31: IRP structure and scope | D31: 1. Obtain the current incident response plan (IRP) and verify it is specific to technology incidents affecting capital market operations. 2. Review the plan structure to confirm it addresses all phases: preparation, identification, containment, eradication, recovery, and lessons learned. 3. Verify the plan defines scope boundaries — which systems, services, and scenarios are covered. 4. Confirm the IRP has been reviewed and approved by senior management within the last 12 months (per sampling methodology for annual processes). | E31: Incident response plan document; IRP approval records (last 12 months); scope definition covering capital market systems | F31: Inspection | M31: =IF(K31="Compliant",3,IF(K31="Partially Compliant",2,IF(K31="Non-Compliant",1,"")))
A32: RIM-5 | B32: Incident Response Plan | C32: Incident classification and severity levels | D32: 1. Review the incident classification scheme and verify it defines severity levels appropriate for capital market operations (e.g., P1 — trading halt or settlement failure, P2 — degraded market access, P3 — non-market-critical system issue). 2. Verify that classification criteria include market impact, client impact, regulatory notification triggers, and financial exposure. 3. Confirm that classification drives response urgency, escalation paths, and resource allocation. 4. Select 8 incident records from the last 12 months (per sampling methodology — high risk, population 16-50) and verify incidents were classified consistently with the defined scheme. | E32: Incident classification matrix; sampled incident records (last 12 months) showing classification applied; severity level definitions | F32: Inspection | M32: =IF(K32="Compliant",3,IF(K32="Partially Compliant",2,IF(K32="Non-Compliant",1,"")))
A33: RIM-5 | B33: Incident Response Plan | C33: Escalation procedures | D33: 1. Review escalation procedures within the IRP, including thresholds that trigger escalation to senior management, the board, and the SC. 2. Verify that escalation timelines are defined for each severity level and account for market trading hours. 3. Confirm that client communication protocols are defined for incidents that affect client-facing services or data. 4. Determine whether escalation procedures include out-of-hours contact arrangements for critical incidents during non-business hours. | E33: Escalation matrix with timelines per severity level; out-of-hours contact arrangements; client communication protocol | F33: Inspection | M33: =IF(K33="Compliant",3,IF(K33="Partially Compliant",2,IF(K33="Non-Compliant",1,"")))
A34: RIM-5 | B34: Incident Response Plan | C34: IR team composition and readiness | D34: 1. Obtain the incident response team roster and verify it includes representatives from IT, security, operations, compliance, legal, and communications. 2. Verify that team member contact details are current and that alternates are designated for key roles. 3. Review training records to confirm IR team members have received incident response training within the last 12 months (per sampling methodology for annual processes). 4. Interview 2 IR team members to assess awareness of their roles and the activation process. | E34: IR team roster with roles and contact details; alternate designations; IR training records (last 12 months) | F34: Inspection / Inquiry | M34: =IF(K34="Compliant",3,IF(K34="Partially Compliant",2,IF(K34="Non-Compliant",1,"")))
A35: RIM-5 | B35: Incident Response Plan | C35: Tabletop exercises and simulations | D35: 1. Obtain records of tabletop exercises or incident simulations conducted within the last 12 months (per sampling methodology for annual processes). 2. Review exercise scenarios to verify they include capital market-specific situations — ransomware during market hours, trading system compromise, settlement data corruption, DDoS on client portal. 3. Verify exercise reports document participation, decisions made, timeline of actions, and findings. 4. Confirm that improvement actions from the last 2 exercises have been tracked and implemented. | E35: Tabletop exercise records (last 12 months); exercise scenarios and reports; improvement action tracking from last 2 exercises | F35: Inspection | M35: =IF(K35="Compliant",3,IF(K35="Partially Compliant",2,IF(K35="Non-Compliant",1,"")))
A36: RIM-5 | B36: Incident Response Plan | C36: IRP review and update cycle | D36: 1. Obtain the IRP review schedule and change log. 2. Verify the plan has been reviewed at least annually (per sampling methodology) and updated after significant incidents, exercise findings, or organisational changes. 3. Review the change log to confirm updates reflect specific findings — not just date changes but substantive content revisions. 4. Confirm that the updated IRP is distributed to all IR team members and that acknowledgement of receipt is recorded. | E36: IRP review schedule and change log; distribution records with acknowledgement; evidence of substantive updates based on findings | F36: Inspection | M36: =IF(K36="Compliant",3,IF(K36="Partially Compliant",2,IF(K36="Non-Compliant",1,"")))
A37: RIM-6 — SC Incident Notification [CRITICAL]
A38: PURPOSE: SC-GL/6-2023 imposes mandatory incident notification obligations on capital market intermediaries because the Securities Commission needs timely visibility into technology disruptions that could affect market operations, investor protection, or systemic stability. This control ensures the intermediary can meet notification deadlines and provide the SC with actionable information. EXPECTATION: The assessor should find documented notification criteria aligned with SC-GL/6-2023 thresholds, a tested notification workflow with defined timelines for initial, interim, and final reporting, pre-approved notification templates, and a tracking mechanism for SC follow-up conditions. The notification process should have been validated through tabletop exercises. KEY RISK: Failure to notify the SC within required timelines is a direct regulatory breach that can result in enforcement action, increased supervisory scrutiny, and loss of the intermediary's licence standing — independent of the underlying incident's severity.
A39: RIM-6 | B39: SC Incident Notification | C39: Notification criteria and thresholds | D39: 1. Obtain the documented notification criteria that define which incidents trigger mandatory reporting to the Securities Commission Malaysia. 2. Verify the criteria are aligned with SC-GL/6-2023 requirements and cover: significant technology disruptions affecting market operations, cyber security breaches involving client data, trading system outages exceeding defined thresholds, and any incident requiring public disclosure. 3. Confirm that notification thresholds are expressed in measurable terms (e.g., outage duration, number of affected clients, financial impact). 4. Review whether the criteria have been reviewed against any updated SC guidance or circulars within the last 12 months (per sampling methodology for annual processes). | E39: SC notification criteria document aligned with SC-GL/6-2023; threshold definitions; criteria review records (last 12 months) | F39: Inspection | M39: =IF(K39="Compliant",3,IF(K39="Partially Compliant",2,IF(K39="Non-Compliant",1,"")))
A40: RIM-6 | B40: SC Incident Notification | C40: Notification workflow and timelines | D40: 1. Obtain the SC notification workflow and verify it defines end-to-end steps from incident identification to SC submission. 2. Verify that the workflow specifies timelines for initial notification, interim updates, and final incident report submission as required by SC-GL/6-2023. 3. Confirm that the workflow identifies authorised persons responsible for preparing and submitting notifications to the SC. 4. Review whether the workflow includes escalation if notification deadlines are at risk of being missed. 5. Determine whether the notification workflow has been tested through tabletop exercises within the last 12 months (per sampling methodology for annual processes). | E40: SC notification workflow document; defined timelines for initial, interim, and final reporting; authorised submitter list; tabletop test records involving SC notification | F40: Inspection | M40: =IF(K40="Compliant",3,IF(K40="Partially Compliant",2,IF(K40="Non-Compliant",1,"")))
A41: RIM-6 | B41: SC Incident Notification | C41: Notification templates and content | D41: 1. Obtain SC incident notification templates and verify they capture all required information: incident description, systems affected, market impact, client impact, containment actions taken, expected resolution timeline, and root cause (if known). 2. Verify that templates are pre-approved and readily accessible to the notification team during an incident. 3. Review any SC notifications submitted in the last 12 months (per sampling methodology for annual processes) (if any) to confirm templates were used and content was complete. 4. Confirm that templates are version-controlled and updated when SC reporting requirements change. | E41: SC incident notification templates; sample completed notifications (last 12 months, if applicable); template version control records | F41: Inspection | M41: =IF(K41="Compliant",3,IF(K41="Partially Compliant",2,IF(K41="Non-Compliant",1,"")))
A42: RIM-6 | B42: SC Incident Notification | C42: SC follow-up and condition tracking | D42: 1. Obtain the register or tracker for SC responses, queries, and conditions arising from incident notifications. 2. Review any SC follow-up items from the last 12 months (per sampling methodology for annual processes) and verify they were addressed within the required timeframes. 3. Verify that a responsible person is assigned to track each SC follow-up item through to closure. 4. Confirm that closure evidence is maintained for all resolved SC follow-up items. | E42: SC follow-up tracker; closure evidence for resolved items; records of SC correspondence (last 12 months) | F42: Inspection | M42: =IF(K42="Compliant",3,IF(K42="Partially Compliant",2,IF(K42="Non-Compliant",1,"")))
A43: RIM-6 | B43: SC Incident Notification | C43: Notification process assurance | D43: 1. Review whether the SC notification process has been independently tested or validated — through tabletop exercise, internal audit, or compliance review — within the last 12 months (per sampling methodology for annual processes). 2. Verify that the test included a scenario that triggered SC notification and measured the entity's ability to meet required timelines. 3. Confirm that findings from the assurance activity were documented and any gaps addressed. 4. Interview the Compliance Officer or CISO to assess confidence in the entity's ability to meet SC notification obligations during a real incident. | E43: Assurance review or tabletop exercise records testing SC notification; findings and remediation records; internal audit or compliance review reports | F43: Inspection / Inquiry | M43: =IF(K43="Compliant",3,IF(K43="Partially Compliant",2,IF(K43="Non-Compliant",1,"")))
A44: RIM-7 — Cyber Incident Coordination
A45: PURPOSE: SC-GL/6-2023 expects capital market intermediaries to coordinate with external parties during cyber incidents because sophisticated attacks often target multiple market participants simultaneously. Effective coordination with SC Malaysia, MyCERT, Bursa Malaysia, and peer intermediaries enables faster threat containment and sector-wide defence. EXPECTATION: The assessor should find documented external communication protocols with defined contact channels and authorised communicators, evidence of active industry working group participation, threat intelligence sharing records, and joint exercise participation within the last 24 months. Contact directories should be verified at least quarterly. KEY RISK: Poor external coordination during a cyber incident leads to delayed threat intelligence sharing, duplicated response efforts, and inability to contain sector-wide attacks — increasing the duration and impact of incidents across the capital market.
A46: RIM-7 | B46: Cyber Incident Coordination | C46: External communication protocols | D46: 1. Obtain documented communication protocols for coordinating with external parties during cyber incidents — SC Malaysia, MyCERT, Bursa Malaysia, peer intermediaries, and law enforcement. 2. Verify the protocols define: which parties to contact, under what circumstances, through which channels, within what timeframes, and who is authorised to communicate. 3. Confirm that contact details for key external coordination partners are maintained and verified at least quarterly (per sampling methodology — last 4 quarters for board/committee records). 4. Review whether the protocols distinguish between notification obligations (regulatory) and voluntary coordination (industry). | E46: External communication protocol document; contact directory for SC, MyCERT, Bursa Malaysia, and peers; contact verification records | F46: Inspection | M46: =IF(K46="Compliant",3,IF(K46="Partially Compliant",2,IF(K46="Non-Compliant",1,"")))
A47: RIM-7 | B47: Cyber Incident Coordination | C47: Industry coordination and working group participation | D47: 1. Obtain records of the entity's participation in industry incident coordination mechanisms — SC working groups, capital market CERTs, Bursa coordination forums, or Financial Services ISAC equivalents. 2. Review participation records from the last 12 months (per sampling methodology for annual processes) to assess frequency and level of engagement. 3. Verify that insights from industry coordination are fed back into the entity's incident response plans and threat intelligence. 4. Interview the CISO to assess the maturity of industry relationships and any barriers to effective coordination. | E47: Industry working group participation records (last 12 months); meeting minutes or briefing notes; evidence of insights incorporated into IRP or threat intelligence | F47: Inspection / Inquiry | M47: =IF(K47="Compliant",3,IF(K47="Partially Compliant",2,IF(K47="Non-Compliant",1,"")))
A48: RIM-7 | B48: Cyber Incident Coordination | C48: Threat intelligence sharing | D48: 1. Obtain records of threat intelligence shared with or received from SC Malaysia, MyCERT, and peer institutions within the last 12 months (per sampling methodology for annual processes). 2. Review whether shared intelligence includes indicators of compromise (IOCs), threat advisories, and sector-specific alerts relevant to capital markets. 3. Select 5 received advisories (per sampling methodology — standard risk, population 6-15) and confirm they were assessed and, where relevant, incorporated into detection rules or response plans. 4. Confirm that information sharing complies with any confidentiality or classification requirements. | E48: Threat intelligence sharing records (last 12 months); sample received advisories with evidence of action taken; confidentiality handling procedures | F48: Inspection | M48: =IF(K48="Compliant",3,IF(K48="Partially Compliant",2,IF(K48="Non-Compliant",1,"")))
A49: RIM-7 | B49: Cyber Incident Coordination | C49: Joint exercises with coordination partners | D49: 1. Obtain records of joint cyber incident exercises conducted with external coordination partners (SC, Bursa, peer intermediaries) within the last 24 months. 2. Review the scope and scenario of joint exercises to verify they tested coordination mechanisms — not just internal response. 3. Verify that findings from joint exercises were documented and improvement actions tracked. 4. Confirm that the entity's communication protocols were updated based on any coordination gaps identified. | E49: Joint exercise participation records (last 24 months); exercise reports and findings; improvement action records; protocol updates based on findings | F49: Inspection | M49: =IF(K49="Compliant",3,IF(K49="Partially Compliant",2,IF(K49="Non-Compliant",1,"")))
A50: RIM-8 — Incident Post-Mortem & Lessons Learned
A51: PURPOSE: SC-GL/6-2023 expects capital market intermediaries to conduct structured post-mortem reviews because recurring incidents indicate systemic control weaknesses. Post-mortem analysis and lessons-learned processes drive continuous improvement in technology risk management and prevent repetition of incidents affecting market operations. EXPECTATION: The assessor should find a defined post-mortem process with severity-based triggers, structured root cause analysis using recognised methodologies, documented lessons learned disseminated to relevant teams, and an improvement action tracker with management reporting. Trend analysis across incidents should identify systemic issues. KEY RISK: Without effective post-mortem processes, the intermediary fails to learn from incidents — leading to recurring disruptions, repeated regulatory findings, and progressive erosion of technology resilience and client confidence.
A52: RIM-8 | B52: Incident Post-Mortem & Lessons Learned | C52: Post-mortem process and governance | D52: 1. Obtain the post-mortem policy or procedure and verify it defines: when a post-mortem is required (severity threshold), the timeframe for completion after incident closure, required participants, and the output format. 2. Verify that the procedure requires involvement of relevant stakeholders beyond IT — including business operations, compliance, and risk management for incidents affecting capital market functions. 3. Confirm that post-mortem completion is tracked as a mandatory step in the incident lifecycle and that non-completion triggers escalation. 4. Review whether the post-mortem process has been approved by senior management. | E52: Post-mortem policy or procedure document; escalation rules for non-completion; management approval records | F52: Inspection | M52: =IF(K52="Compliant",3,IF(K52="Partially Compliant",2,IF(K52="Non-Compliant",1,"")))
A53: RIM-8 | B53: Incident Post-Mortem & Lessons Learned | C53: Root cause analysis | D53: 1. Select 5 significant incident post-mortem reports from the last 12 months (per sampling methodology — standard risk, population 6-15). 2. Review whether each report identifies root causes (not just immediate causes or symptoms) using a structured methodology (e.g., 5-Whys, fishbone analysis, fault tree). 3. Verify that contributing factors are documented separately from root causes — including people, process, and technology factors. 4. Confirm that root cause findings are specific and actionable, not generic statements. | E53: Sampled post-mortem reports (last 12 months); root cause analysis documentation; evidence of structured methodology applied | F53: Inspection | M53: =IF(K53="Compliant",3,IF(K53="Partially Compliant",2,IF(K53="Non-Compliant",1,"")))
A54: RIM-8 | B54: Incident Post-Mortem & Lessons Learned | C54: Lessons learned capture and dissemination | D54: 1. Review the sampled 5 post-mortem reports (per sampling methodology — standard risk, population 6-15) and verify that lessons learned are explicitly documented and distinguished from root causes and improvement actions. 2. Verify that lessons learned are disseminated to relevant teams — not just the incident response team but also development, operations, and business teams as appropriate. 3. Confirm that lessons learned from incidents affecting capital market operations are reported to senior management or the board. 4. Determine whether a lessons-learned repository or knowledge base is maintained and accessible to relevant personnel. | E54: Lessons learned sections in post-mortem reports; dissemination records (emails, briefings, knowledge base entries); board or management reporting of lessons learned | F54: Inspection | M54: =IF(K54="Compliant",3,IF(K54="Partially Compliant",2,IF(K54="Non-Compliant",1,"")))
A55: RIM-8 | B55: Incident Post-Mortem & Lessons Learned | C55: Improvement action tracking and trend analysis | D55: 1. Obtain the improvement action tracker and verify that all actions from post-mortem reviews within the last 12 months (per sampling methodology for annual processes) are logged with assigned owners, priorities, and target completion dates. 2. Review completion rates — determine the percentage of improvement actions closed on time versus overdue. 3. Verify that trend analysis is conducted across incidents to identify recurring root causes or systemic issues. 4. Confirm that systemic findings have led to broader remediation initiatives, not just point fixes. 5. Review whether improvement action status is reported to senior management periodically. | E55: Improvement action tracker with assigned owners and target dates; trend analysis report; management reporting on improvement action status; evidence of systemic remediation initiatives | F55: Inspection | M55: =IF(K55="Compliant",3,IF(K55="Partially Compliant",2,IF(K55="Non-Compliant",1,"")))
A57: This work program is constructed for educational purposes. Customise for your engagement. Not legal or regulatory advice. AI-generated content — review and validate before use.

Sheet Third-Party & Cloud
A1: Ref | B1: Control | C1: Sub-Procedure | D1: Assessment Procedures | E1: Expected Evidence | F1: Method | G1: Procedures Performed | H1: Evidence Obtained | I1: Evidence Ref | J1: Observation / Findings | K1: Conclusion | L1: Recommendations | M1: Score
A2: TPC-1 — Third-Party Risk Assessment
A3: PURPOSE: SC-GL/6-2023 requires capital market intermediaries to assess and manage third-party technology risks because outsourced services supporting trading, clearing, and settlement carry the same operational risk as in-house systems. Vendor risk assessment ensures the intermediary understands and controls risks introduced through its technology supply chain. EXPECTATION: The assessor should find a documented vendor risk tiering methodology that differentiates capital market-specific categories (exchange connectivity, market data, clearing interfaces), completed due diligence assessments for critical vendors with security posture validation, ongoing risk monitoring proportionate to tier, and annual reassessments with year-over-year trend analysis. KEY RISK: Unassessed third-party risks can materialise as trading system outages, client data breaches, or settlement failures originating from vendor infrastructure — for which the intermediary remains fully accountable to the SC regardless of the outsourcing arrangement.
A4: TPC-1 | B4: Third-Party Risk Assessment | C4: Vendor risk tiering methodology | D4: 1. Obtain the vendor risk tiering methodology and classification criteria, confirming it addresses service criticality, data access (client PII, market data), and capital market system dependencies (trading platforms, exchange connectivity, clearing interfaces). 2. Verify that tiering criteria differentiate between vendors with access to client data under PDPA, vendors providing market data feeds, and vendors supporting non-critical functions. 3. Review the complete third-party register and confirm all technology service providers are classified by risk tier. 4. Determine whether the tiering methodology has been reviewed and approved within the last 12 months (per sampling methodology for annual processes). | E4: Vendor risk tiering methodology document; Third-party technology service provider register with tier classifications; Board or management approval of tiering criteria; Criteria mapping for capital market-specific vendor categories | F4: Inspection | M4: =IF(K4="Compliant",3,IF(K4="Partially Compliant",2,IF(K4="Non-Compliant",1,"")))
A5: TPC-1 | B5: Third-Party Risk Assessment | C5: Due diligence process for critical vendors | D5: 1. Obtain the due diligence procedures for onboarding new third-party technology providers and confirm they define assessment depth by risk tier. 2. Select 5 critical-tier vendors (per sampling methodology — standard risk, population 6-15), including at least one market data provider or exchange connectivity provider, and review the due diligence assessments conducted at onboarding. 3. Verify that due diligence for critical vendors includes financial stability checks, information security capability assessment, regulatory compliance status, and business continuity arrangements. 4. Confirm that due diligence findings were formally accepted or resulted in documented risk treatment before vendor engagement. | E5: Vendor due diligence procedures; Due diligence assessment reports for sampled vendors; Financial stability and credit checks; Risk acceptance or treatment records for identified findings | F5: Inspection | M5: =IF(K5="Compliant",3,IF(K5="Partially Compliant",2,IF(K5="Non-Compliant",1,"")))
A6: TPC-1 | B6: Third-Party Risk Assessment | C6: Vendor security posture assessment | D6: 1. For the same sample of 5 critical-tier vendors (per sampling methodology), obtain evidence of security posture assessment conducted (security questionnaires, independent security reviews, or assurance reports). 2. Verify that vendors with access to client data or market systems have provided current SOC 2 Type II reports, ISO 27001 certificates, or equivalent independent assurance. 3. Review how assurance report findings (particularly complementary user entity controls) are assessed for relevance to the entity's risk profile. 4. Confirm that vendors providing trading platform services or exchange connectivity have undergone security assessments covering system availability and data integrity. | E6: Completed vendor security questionnaires; SOC 2 Type II reports or ISO 27001 certificates for critical vendors; Security assessment reports for trading system vendors; Assurance report gap analysis or CUEC mapping | F6: Inspection | M6: =IF(K6="Compliant",3,IF(K6="Partially Compliant",2,IF(K6="Non-Compliant",1,"")))
A7: TPC-1 | B7: Third-Party Risk Assessment | C7: Ongoing vendor risk monitoring | D7: 1. Obtain evidence of ongoing risk monitoring activities for critical vendors over the last 12 months (per sampling methodology for annual processes), including periodic risk reviews, threat intelligence related to vendors, and financial health monitoring. 2. Review how changes in vendor risk profile (e.g., data breaches, financial distress, regulatory action) are detected and escalated. 3. Verify that monitoring frequency is proportionate to risk tier — at minimum quarterly for critical-tier vendors providing market infrastructure services. 4. Interview vendor risk management staff to understand how monitoring findings trigger reassessment or remediation. | E7: Vendor risk monitoring reports for last 12 months; Vendor risk alert or notification records; Escalation records for changes in vendor risk profile; Evidence of periodic financial health checks for critical vendors | F7: Inspection / Inquiry | M7: =IF(K7="Compliant",3,IF(K7="Partially Compliant",2,IF(K7="Non-Compliant",1,"")))
A8: TPC-1 | B8: Third-Party Risk Assessment | C8: Annual vendor reassessment | D8: 1. Obtain the schedule of annual vendor reassessments and verify all critical-tier vendors were reassessed within the last 12 months (per sampling methodology for annual processes). 2. Select 5 vendor reassessments (per sampling methodology — standard risk, population 6-15) and confirm the reassessment scope covers security posture, service delivery performance, compliance status, and any changes in sub-contracting arrangements. 3. Verify that reassessment results are compared against prior year to identify trends or deterioration in vendor risk posture. 4. Confirm that reassessment findings are reported to senior management and that remediation actions are tracked to closure. | E8: Annual vendor reassessment schedule and completion records; Reassessment reports for sampled vendors; Year-over-year trend analysis; Management reporting of reassessment findings with remediation tracking | F8: Inspection | M8: =IF(K8="Compliant",3,IF(K8="Partially Compliant",2,IF(K8="Non-Compliant",1,"")))
A9: TPC-2 — Outsourcing Governance
A10: PURPOSE: SC-GL/6-2023 mandates formal outsourcing governance because capital market intermediaries cannot outsource regulatory accountability. Board-level oversight, SC notification for material outsourcing, and robust contractual standards ensure the intermediary retains control over outsourced functions critical to market operations and client protection. EXPECTATION: The assessor should find a board-approved outsourcing policy aligned with SC-GL/6-2023, documented board approval for each material outsourcing arrangement, contracts with mandatory provisions (SLAs, right-to-audit, PDPA compliance, exit provisions), quarterly board reporting on outsourcing risks, and evidence of SC notification compliance. KEY RISK: Weak outsourcing governance results in loss of visibility and control over outsourced market operations, exposing the intermediary to regulatory non-compliance, unmanaged vendor failures, and inability to demonstrate accountability to the SC for outsourced functions.
A11: TPC-2 | B11: Outsourcing Governance | C11: Outsourcing policy alignment with SC-GL/6-2023 | D11: 1. Obtain the outsourcing policy and verify it is aligned with SC-GL/6-2023 requirements, including definitions of material outsourcing, risk assessment requirements, and governance structures. 2. Verify the policy defines what constitutes material outsourcing for capital market intermediaries (e.g., outsourcing of trading operations, clearing/settlement functions, client data processing, or IT infrastructure supporting market operations). 3. Confirm the policy mandates board approval for material outsourcing arrangements, SC notification where required, and periodic review of all outsourcing arrangements. 4. Determine that the policy was reviewed and approved by the board within the last 12 months (per sampling methodology for annual processes) and that staff with outsourcing management responsibilities have been made aware of the policy. | E11: Outsourcing policy document; Board approval records for the policy; SC-GL/6-2023 requirement mapping against policy provisions; Policy distribution and acknowledgement records | F11: Inspection | M11: =IF(K11="Compliant",3,IF(K11="Partially Compliant",2,IF(K11="Non-Compliant",1,"")))
A12: TPC-2 | B12: Outsourcing Governance | C12: Board approval for material outsourcing | D12: 1. Obtain the register of all material outsourcing arrangements and confirm each arrangement has documented board approval. 2. Review board papers for 3 material outsourcing arrangements (per sampling methodology — standard risk, population 1-5: all, or population 6-15: 3) and verify the board was provided with adequate information including risk assessment results, proposed controls and monitoring mechanisms, and impact on capital market operations. 3. Verify that SC notification requirements for material outsourcing have been met where applicable, including outsourcing of critical market infrastructure functions. 4. Confirm that the board has delegated day-to-day outsourcing oversight to an appropriate management committee with defined terms of reference. | E12: Material outsourcing register; Board meeting minutes with outsourcing approval decisions; Board papers with risk assessments and control proposals; SC notification records for material outsourcing; Management committee terms of reference for outsourcing oversight | F12: Inspection | M12: =IF(K12="Compliant",3,IF(K12="Partially Compliant",2,IF(K12="Non-Compliant",1,"")))
A13: TPC-2 | B13: Outsourcing Governance | C13: Contractual standards for outsourcing agreements | D13: 1. Select 5 material outsourcing contracts (per sampling methodology — standard risk, population 6-15), including at least one involving client data processing and one involving trading or market infrastructure services, and inspect for mandatory contractual provisions. 2. Verify each contract includes: defined SLAs with measurable performance targets, right-to-audit clauses permitting the entity and SC to audit the service provider, data protection obligations aligned with PDPA, business continuity and disaster recovery commitments, termination and exit provisions, and regulatory access provisions. 3. Confirm that contracts specify data handling obligations including restrictions on data location, use, and disclosure for client information and market data. 4. Determine whether contract templates have been reviewed by legal counsel with knowledge of SC-GL/6-2023 requirements. | E13: Sample outsourcing contracts (material arrangements); Contract review checklist against SC-GL/6-2023 mandatory provisions; Legal counsel review records; Data protection schedules or annexes within contracts | F13: Inspection | M13: =IF(K13="Compliant",3,IF(K13="Partially Compliant",2,IF(K13="Non-Compliant",1,"")))
A14: TPC-2 | B14: Outsourcing Governance | C14: Outsourcing risk reporting to the board | D14: 1. Obtain outsourcing risk reports to the board for the last 4 quarters (per sampling methodology for board/committee reports) and verify reporting cadence is maintained. 2. Review report content and confirm it covers: vendor performance against SLAs, significant incidents involving outsourced services, changes in vendor risk profile, compliance with contractual obligations, and any new or terminated outsourcing arrangements. 3. Verify that board actions or decisions arising from outsourcing risk reports are documented and tracked. 4. Interview the COO or outsourcing governance lead to understand how the reporting captures risks from outsourced capital market functions (e.g., trade execution, settlement, custody). | E14: Quarterly outsourcing risk reports for last 4 quarters; Board meeting minutes showing discussion of outsourcing reports; Action tracking records from board outsourcing decisions; Reporting templates and data sources | F14: Inspection / Inquiry | M14: =IF(K14="Compliant",3,IF(K14="Partially Compliant",2,IF(K14="Non-Compliant",1,"")))
A15: TPC-2 | B15: Outsourcing Governance | C15: SC notification compliance for outsourcing | D15: 1. Obtain records of SC notifications submitted for material outsourcing arrangements and verify completeness against the material outsourcing register. 2. Review notification content to confirm it includes the information required by SC-GL/6-2023, including description of outsourced function, risk assessment summary, and controls implemented. 3. Verify that SC responses or conditions (if any) have been addressed and tracked to closure. 4. Determine whether the entity maintains a tracking mechanism for SC notification requirements across all material outsourcing arrangements. | E15: SC notification records for material outsourcing; Material outsourcing register cross-referenced to notification status; SC response and condition tracking records; Notification workflow documentation | F15: Inspection / Confirmation | M15: =IF(K15="Compliant",3,IF(K15="Partially Compliant",2,IF(K15="Non-Compliant",1,"")))
A16: TPC-3 — Vendor Performance Monitoring
A17: PURPOSE: SC-GL/6-2023 requires ongoing performance monitoring of technology vendors because capital market operations depend on continuous, reliable third-party service delivery. SLA monitoring with defined escalation procedures ensures vendor underperformance is detected early and addressed before it degrades trading, clearing, or settlement operations. EXPECTATION: The assessor should find a structured SLA monitoring framework with metrics calibrated to capital market operational requirements, regular performance reporting for critical vendors, defined escalation procedures for SLA breaches, and evidence of periodic vendor governance reviews driving continuous improvement. KEY RISK: Unmonitored vendor performance allows service degradation to go undetected until it causes trading delays, market data gaps, or settlement processing failures — by which point the impact on market operations and client service has already occurred.
A18: TPC-3 | B18: Vendor Performance Monitoring | C18: SLA monitoring framework and metrics | D18: 1. Obtain the SLA monitoring framework and verify it defines how vendor performance is measured, reported, and escalated for all outsourced technology services. 2. Verify that SLA metrics are defined for critical capital market vendor categories: market data providers (latency, accuracy, availability), trading platform vendors (uptime, order execution performance), and exchange connectivity providers (connection availability, failover times). 3. Confirm that SLA measurement is based on independent monitoring or verified vendor reporting rather than unverified vendor self-reporting alone. 4. Review whether SLA thresholds and targets have been calibrated against capital market operational requirements (e.g., trading hours availability, settlement window performance). | E18: SLA monitoring framework document; Defined SLA metrics for each critical vendor category; Independent monitoring tool configurations or reports; SLA threshold calibration records aligned to market operational requirements | F18: Inspection | M18: =IF(K18="Compliant",3,IF(K18="Partially Compliant",2,IF(K18="Non-Compliant",1,"")))
A19: TPC-3 | B19: Vendor Performance Monitoring | C19: Vendor performance reporting | D19: 1. Obtain monthly performance reports for 5 critical vendors (per sampling methodology — standard risk, population 6-15) from the last 3-6 months (per sampling methodology for operational records), including at least one market data provider or exchange connectivity provider. 2. Verify SLA metrics are tracked against agreed targets, deviations are highlighted, and trends are analysed. 3. Review how performance data is aggregated and presented to management, including dashboards or summary reports. 4. Confirm that performance reports differentiate between minor SLA misses and material performance degradation affecting capital market operations. | E19: Monthly vendor performance reports for critical vendors (last 3-6 months); SLA compliance dashboards or scorecards; Performance trend analysis; Management summary reports on vendor performance | F19: Inspection | M19: =IF(K19="Compliant",3,IF(K19="Partially Compliant",2,IF(K19="Non-Compliant",1,"")))
A20: TPC-3 | B20: Vendor Performance Monitoring | C20: SLA breach escalation procedures | D20: 1. Obtain the escalation procedures for SLA breaches and verify they define escalation tiers, timelines, and responsible parties. 2. Select 3 instances of SLA breaches from the last 12 months (per sampling methodology — standard risk, population 1-5: all) and trace the escalation process to verify timely notification, root cause analysis, and remediation actions. 3. Verify that service credits or contractual penalties were assessed and applied where applicable. 4. Confirm that persistent underperformance triggers formal remediation plans or consideration of vendor replacement, particularly for vendors supporting trading or settlement operations. | E20: SLA breach escalation procedures; SLA breach records with escalation trail for sampled incidents; Root cause analysis and remediation action records; Service credit or penalty application records; Remediation plans for persistent underperformance | F20: Inspection | M20: =IF(K20="Compliant",3,IF(K20="Partially Compliant",2,IF(K20="Non-Compliant",1,"")))
A21: TPC-3 | B21: Vendor Performance Monitoring | C21: Periodic vendor relationship reviews | D21: 1. Obtain records of periodic vendor governance meetings or relationship reviews for 5 critical vendors (per sampling methodology — standard risk, population 6-15) from the last 12 months (per sampling methodology for annual processes). 2. Review meeting minutes or action logs and verify discussions covered: service delivery performance, upcoming changes or enhancements, risk and compliance matters, and strategic alignment. 3. Confirm that action items from governance meetings are tracked to closure. 4. Interview the service management team to understand how vendor relationship reviews feed into annual reassessment and contract renewal decisions for capital market service providers. | E21: Vendor governance meeting minutes or records for critical vendors; Action item tracking logs; Meeting attendance records; Relationship review summary reports | F21: Inspection / Inquiry | M21: =IF(K21="Compliant",3,IF(K21="Partially Compliant",2,IF(K21="Non-Compliant",1,"")))
A22: TPC-4 — Fourth-Party Oversight
A23: PURPOSE: SC-GL/6-2023 expects intermediaries to look beyond direct vendors because capital market technology supply chains often involve sub-contractors who access client data or operate critical infrastructure. Fourth-party oversight ensures the intermediary understands and manages concentration risks and supply chain dependencies that could disrupt market operations. EXPECTATION: The assessor should find a fourth-party register with disclosed sub-contractors for critical vendors, risk assessments for critical supply chains (particularly trading platform and market data chains), contractual provisions requiring sub-contractor disclosure and flow-down obligations, and concentration risk analysis identifying shared infrastructure dependencies. KEY RISK: Unmanaged fourth-party risk creates hidden single points of failure — multiple critical vendors may depend on the same sub-contractor, and a fourth-party failure can simultaneously disrupt trading, market data, and settlement services.
A24: TPC-4 | B24: Fourth-Party Oversight | C24: Sub-contractor disclosure and register | D24: 1. Obtain the fourth-party register or sub-contractor disclosure records for all critical service providers and verify completeness against contractual disclosure requirements. 2. Verify that critical vendors (market data providers, trading platform vendors, exchange connectivity providers) have disclosed all sub-contractors that access client data or market systems. 3. Confirm that sub-contractor disclosures include the nature of services provided, data access granted, and geographic location of service delivery. 4. Review whether the entity has a process to receive and act on notifications of sub-contractor changes from critical vendors. | E24: Fourth-party register or sub-contractor disclosure records; Contractual disclosure requirement clauses; Sub-contractor change notification records; Process documentation for managing sub-contractor disclosures | F24: Inspection | M24: =IF(K24="Compliant",3,IF(K24="Partially Compliant",2,IF(K24="Non-Compliant",1,"")))
A25: TPC-4 | B25: Fourth-Party Oversight | C25: Fourth-party risk assessment | D25: 1. Select 3 critical supply chains (per sampling methodology — standard risk, population 1-5: all; e.g., trading platform vendor and its infrastructure sub-contractors; market data provider and its data source aggregators) and review fourth-party risk assessments conducted. 2. Verify that assessments evaluate the impact of fourth-party failure on capital market operations, including trading continuity, settlement processing, and client data protection. 3. Confirm that risk assessments consider geographic and jurisdictional risks for fourth parties operating outside Malaysia, particularly where client data under PDPA may be accessed. 4. Determine whether fourth-party risk assessment results are integrated into the overall vendor risk profile for the primary service provider. | E25: Fourth-party risk assessment reports for critical supply chains; Supply chain mapping diagrams; Jurisdictional risk analysis for offshore fourth parties; Integrated vendor risk profiles reflecting fourth-party risks | F25: Inspection | M25: =IF(K25="Compliant",3,IF(K25="Partially Compliant",2,IF(K25="Non-Compliant",1,"")))
A26: TPC-4 | B26: Fourth-Party Oversight | C26: Contractual provisions for sub-contracting | D26: 1. Review contracts with 5 critical vendors (per sampling methodology — standard risk, population 6-15) and verify they include provisions requiring prior approval or notification before engaging new sub-contractors for services involving client data or market systems. 2. Confirm contracts include flow-down requirements ensuring sub-contractors meet the same security, data protection, and confidentiality obligations as the primary vendor. 3. Verify that contracts reserve the entity's right (and the SC's right) to audit sub-contractors providing critical services. 4. Determine whether contracts include provisions for termination if sub-contracting arrangements materially change the risk profile. | E26: Sub-contracting clauses in critical vendor contracts; Flow-down obligation provisions; Audit right provisions extending to sub-contractors; Termination trigger clauses related to sub-contracting changes | F26: Inspection | M26: =IF(K26="Compliant",3,IF(K26="Partially Compliant",2,IF(K26="Non-Compliant",1,"")))
A27: TPC-4 | B27: Fourth-Party Oversight | C27: Concentration risk assessment | D27: 1. Obtain or construct a supply chain dependency map for critical capital market services and identify where multiple vendors depend on the same fourth party (e.g., multiple vendors using the same CSP, or common market data aggregator). 2. Verify that concentration risks have been formally assessed, particularly for shared infrastructure dependencies affecting trading, clearing, or settlement. 3. Review whether mitigating actions have been identified and implemented for material concentration risks (e.g., alternative providers, multi-cloud arrangements, diversified data feeds). 4. Interview vendor risk management staff to understand how fourth-party concentration risks are monitored on an ongoing basis. | E27: Supply chain dependency map or concentration risk analysis; Concentration risk assessment report; Mitigation action plans for identified concentration risks; Monitoring reports for ongoing concentration risk tracking | F27: Inspection / Inquiry | M27: =IF(K27="Compliant",3,IF(K27="Partially Compliant",2,IF(K27="Non-Compliant",1,"")))
A28: TPC-5 — Cloud Risk Assessment
A29: PURPOSE: SC-GL/6-2023 requires risk assessment before cloud adoption because cloud deployments for capital market systems introduce shared responsibility complexity, multi-tenancy risks, and data sovereignty considerations unique to the Malaysian regulatory environment. A structured cloud risk assessment framework ensures these risks are evaluated against PDPA and SC expectations before workloads are migrated. EXPECTATION: The assessor should find a board-approved cloud risk assessment framework addressing shared responsibility, data residency, and multi-tenancy risks, completed risk assessments for all current cloud engagements (performed before adoption, not retrospectively), shared responsibility matrices with evidence of entity-side control implementation, and current CSP assurance reports with CUEC gap analysis. KEY RISK: Adopting cloud services without adequate risk assessment can result in client data being stored in non-compliant jurisdictions, unmanaged shared responsibility gaps, and reliance on CSP controls that do not meet SC or PDPA requirements — creating regulatory exposure that is difficult to remediate post-deployment.
A30: TPC-5 | B30: Cloud Risk Assessment | C30: Cloud risk assessment framework | D30: 1. Obtain the cloud risk assessment framework or methodology and verify it addresses shared responsibility, multi-tenancy, data residency, vendor lock-in, and regulatory requirements specific to Malaysian capital market data. 2. Verify the framework mandates risk assessment before any new cloud adoption involving client data (subject to PDPA), market data, or capital market system workloads. 3. Confirm the framework defines risk acceptance criteria and approval authorities for cloud deployments at different risk levels. 4. Determine whether the framework has been reviewed within the last 12 months (per sampling methodology for annual processes) and approved by senior management or the board. | E30: Cloud risk assessment framework or methodology document; Framework approval records; Risk acceptance criteria and approval authority matrix; Framework review and update records | F30: Inspection | M30: =IF(K30="Compliant",3,IF(K30="Partially Compliant",2,IF(K30="Non-Compliant",1,"")))
A31: TPC-5 | B31: Cloud Risk Assessment | C31: Shared responsibility model documentation | D31: 1. Obtain the shared responsibility matrices for all current CSP engagements involving capital market systems or client data. 2. Verify each matrix clearly delineates security responsibilities between the entity and the CSP across infrastructure, platform, application, and data layers. 3. Select 3 CSP engagements (per sampling methodology — standard risk, population 1-5: all) and confirm the entity has implemented its side of the shared responsibility obligations (e.g., IAM configuration, data encryption, network security controls). 4. Review whether shared responsibility matrices are reviewed and updated when CSPs change their service models or introduce new features. | E31: Shared responsibility matrices for each CSP engagement; Evidence of entity-side control implementation for sampled engagements; CSP service model change tracking records; Responsibility matrix review and update log | F31: Inspection | M31: =IF(K31="Compliant",3,IF(K31="Partially Compliant",2,IF(K31="Non-Compliant",1,"")))
A32: TPC-5 | B32: Cloud Risk Assessment | C32: Data residency and sovereignty assessment | D32: 1. Obtain the data residency assessment for cloud-hosted capital market data and verify it identifies where client information (subject to PDPA) and market data are physically stored and processed. 2. Verify that data residency requirements have been assessed against PDPA cross-border transfer provisions and SC-GL/6-2023 expectations for data sovereignty. 3. Confirm that CSP contracts specify permitted data storage jurisdictions and that technical controls enforce residency restrictions (e.g., region-locked deployments). 4. Review whether the entity has assessed the legal and regulatory implications of data being accessible from jurisdictions outside Malaysia, even if stored domestically. | E32: Data residency assessment report; PDPA cross-border transfer compliance analysis; CSP contractual data residency provisions; Technical configuration evidence for region-locked deployments; Legal opinion on jurisdictional data access risks | F32: Inspection | M32: =IF(K32="Compliant",3,IF(K32="Partially Compliant",2,IF(K32="Non-Compliant",1,"")))
A33: TPC-5 | B33: Cloud Risk Assessment | C33: CSP certification and assurance review | D33: 1. Obtain current CSP certifications and independent assurance reports (SOC 2 Type II, ISO 27001, CSA STAR) for all CSPs hosting capital market systems or client data. 2. Verify that assurance reports are current (issued within the last 12 months, per sampling methodology for annual processes) and that the scope covers the specific services and regions used by the entity. 3. Review complementary user entity controls (CUECs) identified in SOC 2 reports and verify the entity has implemented them. 4. Confirm that any qualifications, exceptions, or findings in assurance reports have been assessed for impact on the entity's risk profile and addressed where necessary. | E33: CSP SOC 2 Type II reports; ISO 27001 certificates for CSPs; CSA STAR certification records; CUEC implementation evidence; Gap analysis for assurance report findings or qualifications | F33: Inspection | M33: =IF(K33="Compliant",3,IF(K33="Partially Compliant",2,IF(K33="Non-Compliant",1,"")))
A34: TPC-5 | B34: Cloud Risk Assessment | C34: Cloud security posture assessment | D34: 1. Obtain evidence of cloud security posture assessments conducted for environments hosting capital market workloads, including configuration reviews and compliance checks. 2. Verify that cloud security posture management (CSPM) tools or processes are in place to detect misconfigurations, excessive permissions, and non-compliant resource deployments. 3. Select 3 cloud environments (per sampling methodology — standard risk, population 1-5: all) and review security posture assessment results, including findings, severity ratings, and remediation status. 4. Confirm that critical and high-severity cloud security findings are remediated within defined SLAs and that residual risks are formally accepted by appropriate management. | E34: Cloud security posture assessment reports; CSPM tool configuration and output; Remediation tracking records for cloud security findings; Risk acceptance records for residual cloud security risks | F34: Inspection | M34: =IF(K34="Compliant",3,IF(K34="Partially Compliant",2,IF(K34="Non-Compliant",1,"")))
A35: TPC-5 | B35: Cloud Risk Assessment | C35: Cloud risk assessment completion for current engagements | D35: 1. Obtain an inventory of all current cloud engagements involving client data or market systems and cross-reference against completed cloud risk assessments. 2. Verify that each engagement had a risk assessment completed before cloud adoption, not retrospectively. 3. Select 3 completed cloud risk assessments (per sampling methodology — standard risk, population 1-5: all) and confirm they address all framework requirements including shared responsibility, data residency, multi-tenancy risks, and capital market-specific considerations. 4. Determine whether cloud risk assessments are refreshed periodically (at minimum annually, per sampling methodology for annual processes) or when material changes occur to the cloud deployment. | E35: Cloud engagement inventory; Completed cloud risk assessments for all engagements; Risk assessment completion dates versus cloud adoption dates; Periodic reassessment records | F35: Inspection | M35: =IF(K35="Compliant",3,IF(K35="Partially Compliant",2,IF(K35="Non-Compliant",1,"")))
A36: TPC-6 — Cloud Data Governance
A37: PURPOSE: SC-GL/6-2023 requires cloud data governance because capital market client data stored in cloud environments remains subject to PDPA and SC supervisory expectations regardless of hosting location. Effective cloud data governance ensures data classification, encryption, access controls, and residency enforcement are maintained to the same standard as on-premises systems. EXPECTATION: The assessor should find data classification applied and technically enforced in cloud environments, customer-managed encryption keys (BYOK) for client PII and market-sensitive data, IAM policies enforcing least-privilege with MFA for all sensitive access, active data access monitoring with anomaly detection, and data residency controls preventing non-compliant replication or processing. KEY RISK: Weak cloud data governance exposes client PII to unauthorised access, data residency violations, or undetected exfiltration — any of which can trigger PDPA enforcement action, SC sanctions, and loss of client trust in the intermediary's data stewardship.
A38: TPC-6 | B38: Cloud Data Governance | C38: Data classification in cloud environments | D38: 1. Obtain the inventory of data types stored in cloud environments and verify classification labels are applied consistent with the entity's data classification scheme. 2. Verify that classification distinguishes between client PII (subject to PDPA), market-sensitive data, trading data, and general corporate data, with protection levels defined for each. 3. Select 3 cloud environments (per sampling methodology — standard risk, population 1-5: all) and confirm that data classification labels are technically enforced (e.g., resource tagging, metadata labels, automated classification tools). 4. Review whether data classification in cloud is periodically reviewed to capture new data types or changes in sensitivity as capital market operations evolve. | E38: Cloud data inventory with classification labels; Data classification scheme applied to cloud data types; Resource tagging or metadata label configurations for sampled environments; Classification review records | F38: Inspection | M38: =IF(K38="Compliant",3,IF(K38="Partially Compliant",2,IF(K38="Non-Compliant",1,"")))
A39: TPC-6 | B39: Cloud Data Governance | C39: Encryption and key management (BYOK) | D39: 1. Verify encryption controls for sensitive data in cloud environments: inspect encryption configuration for data at rest and data in transit for all cloud environments hosting client data or market data. 2. Confirm that customer-managed keys (BYOK or HYOK) are used for encrypting client PII and market-sensitive data, rather than relying solely on CSP-managed keys. 3. Review key management procedures including key generation, rotation schedules (per sampling methodology — last 3-6 months for operational records), access controls on key management systems, and key lifecycle management. 4. Determine whether encryption key management has been assessed for compliance with PDPA data protection requirements and whether key escrow or recovery procedures are documented. | E39: Encryption configuration evidence for cloud environments (at-rest and in-transit); Customer-managed key (BYOK) deployment records; Key management procedure documentation; Key rotation schedules and execution logs; Key access control configurations | F39: Inspection | M39: =IF(K39="Compliant",3,IF(K39="Partially Compliant",2,IF(K39="Non-Compliant",1,"")))
A40: TPC-6 | B40: Cloud Data Governance | C40: Cloud access controls and privileged access | D40: 1. Review IAM policies and access control configurations for cloud environments hosting client data, including role definitions, least-privilege enforcement, and segregation of duties. 2. Verify that multi-factor authentication is enforced for all access to cloud environments containing client PII or market data, particularly for privileged and administrative accounts. 3. Obtain the privileged access register for cloud environments and verify that privileged access is limited, justified, reviewed at least quarterly (per sampling methodology — last 4 quarters for board/committee records), and subject to enhanced monitoring. 4. Confirm that access provisioning and de-provisioning processes are timely and that access reviews have been completed within the last quarter. | E40: IAM policy configurations for cloud environments; MFA enforcement evidence; Privileged access register with justification records; Quarterly access review records; Access provisioning and de-provisioning logs | F40: Inspection | M40: =IF(K40="Compliant",3,IF(K40="Partially Compliant",2,IF(K40="Non-Compliant",1,"")))
A41: TPC-6 | B41: Cloud Data Governance | C41: Cloud data access monitoring and anomaly detection | D41: 1. Review cloud access logs and audit trails for the last 3-6 months (per sampling methodology for operational records) to verify that data access monitoring is active for environments hosting client data and market data. 2. Verify that logging covers all access to sensitive data including administrative actions, data exports, bulk queries, and API access to client information. 3. Confirm that anomalous access patterns (e.g., unusual data downloads, access from unexpected locations, off-hours privileged access) are detected and investigated. 4. Select 3 anomaly alerts or investigations from the last 3-6 months (per sampling methodology — standard risk, population 1-5: all) and verify they were responded to within defined SLAs, with documented investigation outcomes. | E41: Cloud access logs and audit trail configurations; Data access monitoring dashboard or reports; Anomaly detection rule configurations; Investigation records for sampled anomaly alerts; Alert response SLA compliance reports | F41: Inspection | M41: =IF(K41="Compliant",3,IF(K41="Partially Compliant",2,IF(K41="Non-Compliant",1,"")))
A42: TPC-6 | B42: Cloud Data Governance | C42: Data residency enforcement in cloud | D42: 1. Inspect cloud deployment configurations for environments hosting Malaysian capital market client data and verify that data residency restrictions are technically enforced (e.g., region-locked resource groups, geo-fencing policies). 2. Verify that data residency controls prevent data replication, backup, or processing in non-approved jurisdictions. 3. Review CSP data residency commitment documentation and confirm it aligns with PDPA cross-border data transfer requirements. 4. Confirm that data residency compliance is monitored on an ongoing basis (per sampling methodology — last 30 days for continuous monitoring) and that any residency violations are detected and escalated promptly. | E42: Cloud deployment region configurations; Geo-fencing or region-lock policy settings; CSP data residency commitment documentation; Data residency monitoring reports; Residency violation detection and escalation records | F42: Inspection | M42: =IF(K42="Compliant",3,IF(K42="Partially Compliant",2,IF(K42="Non-Compliant",1,"")))
A43: TPC-7 — Cloud Exit Strategy
A44: PURPOSE: SC-GL/6-2023 requires cloud exit strategies because capital market intermediaries must be able to migrate away from a CSP without disrupting market operations or compromising client data. Exit planning ensures the intermediary avoids vendor lock-in and can maintain continuity of trading, clearing, and settlement services during any transition. EXPECTATION: The assessor should find documented exit plans for all material cloud deployments with timeline and cost estimates, tested data portability using open standards and non-proprietary formats, identified alternative providers assessed for capital market suitability, and integration of cloud contingency scenarios into the BCP. KEY RISK: Without a viable exit strategy, the intermediary is locked into a CSP with no practical ability to migrate — creating existential risk if the CSP terminates service, experiences prolonged outage, or changes terms that conflict with SC or PDPA requirements.
A45: TPC-7 | B45: Cloud Exit Strategy | C45: Exit plan documentation for material cloud deployments | D45: 1. Obtain documented exit plans for all material cloud deployments hosting capital market systems or client data and verify they exist for each material engagement. 2. Verify each exit plan covers: data extraction procedures, service migration approach, timeline estimates and cost projections, communication plan for stakeholders, and continuity of capital market operations during transition. 3. Confirm that exit plans address the handling of client data under PDPA during and after migration, including secure deletion from the departing CSP. 4. Determine whether exit plans have been reviewed and updated within the last 12 months (per sampling methodology for annual processes) and approved by the CTO or equivalent. | E45: Cloud exit plans for all material deployments; Exit plan approval records; Timeline and cost estimates for each exit scenario; PDPA data handling procedures during exit; Exit plan review and update log | F45: Inspection | M45: =IF(K45="Compliant",3,IF(K45="Partially Compliant",2,IF(K45="Non-Compliant",1,"")))
A46: TPC-7 | B46: Cloud Exit Strategy | C46: Data portability and format standards | D46: 1. Review cloud workload designs for portability considerations, including use of open standards, containerisation, and avoidance of proprietary lock-in for critical capital market services. 2. Verify that data export formats have been defined and tested for all material data categories (client records, trading data, market data, configuration data) ensuring data can be extracted in usable, non-proprietary formats. 3. Confirm that CSP contracts include provisions for data retrieval timelines, format commitments, and assistance obligations upon exit. 4. Review contractual provisions for data deletion by the CSP post-termination and verify they align with PDPA data retention and destruction requirements. | E46: Cloud architecture documentation showing portability considerations; Data export format specifications and test results; CSP contractual exit assistance provisions; Data deletion obligation clauses; Vendor lock-in assessment for critical services | F46: Inspection | M46: =IF(K46="Compliant",3,IF(K46="Partially Compliant",2,IF(K46="Non-Compliant",1,"")))
A47: TPC-7 | B47: Cloud Exit Strategy | C47: Migration testing and validation | D47: 1. Obtain records of data extraction and migration testing conducted for material cloud deployments, verifying tests were performed within the last 12 months (per sampling methodology for annual processes). 2. Verify that migration tests include end-to-end data extraction, integrity validation (record counts, checksums), and confirmation that all data categories can be retrieved in agreed formats. 3. Review test results including time to extract, data completeness verification, and any issues encountered and their resolution. 4. Confirm that migration testing for capital market data covers trading records, client data, and regulatory reporting data to ensure continuity of SC and Bursa Malaysia reporting obligations. | E47: Data migration test plans and execution records; Test results with data integrity validation (checksums, record counts); Time-to-extract measurements; Issue logs and resolution records from migration tests; Coverage confirmation for regulatory reporting data | F47: Inspection | M47: =IF(K47="Compliant",3,IF(K47="Partially Compliant",2,IF(K47="Non-Compliant",1,"")))
A48: TPC-7 | B48: Cloud Exit Strategy | C48: Alternative provider identification and contingency | D48: 1. Interview the CTO or cloud architecture team to understand identified alternative CSPs or on-premises fallback options for each critical cloud service. 2. Verify that alternative providers have been assessed for capability to host capital market workloads, including compliance with data residency requirements, availability of required certifications, and ability to meet performance SLAs. 3. Review whether transition timelines and effort estimates have been developed for migrating to alternative providers. 4. Confirm that contingency arrangements are documented and integrated into the entity's business continuity planning for scenarios involving CSP failure or sudden termination. | E48: Alternative provider assessment records; Capability comparison matrix for alternative CSPs; Transition timeline and effort estimates; BCP integration documentation for cloud contingency scenarios; CTO or cloud architecture team interview notes | F48: Inspection / Inquiry | M48: =IF(K48="Compliant",3,IF(K48="Partially Compliant",2,IF(K48="Non-Compliant",1,"")))
A50: This work program is constructed for educational purposes. Customise for your engagement. Not legal or regulatory advice. AI-generated content — review and validate before use.

Sheet Data & Emerging Technology
A1: Ref | B1: Control | C1: Sub-Procedure | D1: Assessment Procedures | E1: Expected Evidence | F1: Method | G1: Procedures Performed | H1: Evidence Obtained | I1: Evidence Ref | J1: Observation / Findings | K1: Conclusion | L1: Recommendations | M1: Score
A2: DET-1 — Data Governance Framework
A3: PURPOSE: SC-GL/6-2023 requires capital market intermediaries to establish a comprehensive data governance framework to ensure that data used in trading, valuation, client servicing, and regulatory reporting is managed as a strategic asset with clear ownership and accountability. Effective data governance underpins the integrity of capital market operations and supports regulatory confidence in the intermediary's ability to produce reliable data for supervisory purposes. EXPECTATION: The assessor should expect to find a formally approved data governance framework with clearly defined roles (data owners, stewards, custodians), a data classification scheme applied across critical data domains, data quality standards with measurable metrics, and lifecycle management procedures aligned with SC record-keeping and PDPA requirements. Governance reporting should be embedded in board or management committee agendas with regular cadence. KEY RISK: Without a data governance framework, the intermediary risks data quality failures that could result in incorrect NAV calculations, erroneous trade reporting, regulatory non-compliance, and inability to respond to SC examination requests with reliable data.
A4: DET-1 | B4: Data Governance Framework | C4: Data governance roles & accountability | D4: 1. Obtain the data governance framework document and verify it defines data owners, data stewards, and data custodians with clear accountability for market data, client data, and operational data. 2. Review the reporting structure for data governance, confirming the CDO or equivalent reports to senior management and that data governance is a standing agenda item at a board or management committee. Obtain board or committee reports from the last 4 quarters (per sampling methodology) to verify regular reporting cadence. 3. Verify that data ownership is formally assigned for each critical data domain (trade data, client portfolio data, NAV data, market reference data) and that owners acknowledge their responsibilities. | E4: Data governance framework with defined roles and accountability matrix; Board or management committee minutes from last 4 quarters referencing data governance reporting; Data ownership register covering trade data, client portfolios, and market data domains | F4: Inspection / Inquiry | M4: =IF(K4="Compliant",3,IF(K4="Partially Compliant",2,IF(K4="Non-Compliant",1,"")))
A5: DET-1 | B5: Data Governance Framework | C5: Data classification scheme | D5: 1. Obtain the data classification scheme and verify it defines classification levels (e.g., public, internal, confidential, restricted) with handling requirements for each level. 2. Select a sample of 5 data assets (per sampling methodology, from a population of 6-15) across market data systems, client databases, and trading systems to verify classification labels have been applied consistently. 3. Confirm that the classification scheme addresses capital market-specific data types including Bursa market data feeds, Bloomberg/Reuters terminal data, client CDS account information, and NAV calculation inputs. | E5: Data classification policy with defined levels and handling requirements; Classification labels applied to 5 sampled data assets across market data, client, and trading systems; Data asset inventory with classification assignments | F5: Inspection | M5: =IF(K5="Compliant",3,IF(K5="Partially Compliant",2,IF(K5="Non-Compliant",1,"")))
A6: DET-1 | B6: Data Governance Framework | C6: Data quality standards & monitoring | D6: 1. Review data quality standards and verify they define accuracy, completeness, timeliness, and consistency metrics for critical capital market data (trade data, pricing data, client records). 2. Select a sample of 5 data quality reports from the last 3-6 months of operational records (per sampling methodology) and verify that quality metrics are tracked, thresholds are defined, and breaches trigger investigation and remediation. 3. Determine whether data quality monitoring covers data processed by outsourced service providers and cloud-hosted systems. | E6: Data quality standards document with defined metrics and thresholds; Sample of 5 data quality monitoring reports from last 3-6 months; Evidence of remediation actions for data quality issues identified | F6: Inspection | M6: =IF(K6="Compliant",3,IF(K6="Partially Compliant",2,IF(K6="Non-Compliant",1,"")))
